[
  {
    "First Name": "Nikole",
    "Last Name": "Abramova"
  },
  {
    "First Name": "Jasim",
    "Last Name": "Abubakar"
  },
  {
    "First Name": "Lillian",
    "Last Name": "Adams"
  },
  {
    "First Name": "Sally",
    "Last Name": "Alexis"
  },
  {
    "First Name": "Vivienne",
    "Last Name": "Alley"
  },
  {
    "First Name": "Emmett",
    "Last Name": "Armbrister"
  },
  {
    "First Name": "Julia",
    "Last Name": "Arnot"
  },
  {
    "First Name": "Anna",
    "Last Name": "Atanasov"
  },
  {
    "First Name": "William",
    "Last Name": "Atkinson"
  },
  {
    "First Name": "Jackson",
    "Last Name": "Austin"
  },
  {
    "First Name": "Madison",
    "Last Name": "Ayoub"
  },
  {
    "First Name": "Charlotte",
    "Last Name": "Babb"
  },
  {
    "First Name": "Lenna",
    "Last Name": "Baghai"
  },
  {
    "First Name": "William",
    "Last Name": "Bailey"
  },
  {
    "First Name": "Blair",
    "Last Name": "Baker"
  },
  {
    "First Name": "Fallon",
    "Last Name": "Baker"
  },
  {
    "First Name": "Penny",
    "Last Name": "Baldwin"
  },
  {
    "First Name": "Betsy",
    "Last Name": "Bandlamudi"
  },
  {
    "First Name": "Edward",
    "Last Name": "Barnes"
  },
  {
    "First Name": "Jack",
    "Last Name": "Barnes"
  },
  {
    "First Name": "Caroline",
    "Last Name": "Barragan"
  },
  {
    "First Name": "Connor",
    "Last Name": "Beard"
  },
  {
    "First Name": "Valentina",
    "Last Name": "Beck"
  },
  {
    "First Name": "Thaddeus",
    "Last Name": "Beckner"
  },
  {
    "First Name": "Frances",
    "Last Name": "Beecherl"
  },
  {
    "First Name": "Benjamin",
    "Last Name": "Berlin"
  },
  {
    "First Name": "Greyson",
    "Last Name": "Binswanger"
  },
  {
    "First Name": "Charlie",
    "Last Name": "Boan"
  },
  {
    "First Name": "Ryan",
    "Last Name": "Bock"
  },
  {
    "First Name": "Vivian",
    "Last Name": "Boethel"
  },
  {
    "First Name": "James",
    "Last Name": "Bolander"
  },
  {
    "First Name": "Blakely",
    "Last Name": "Boone"
  },
  {
    "First Name": "Alice",
    "Last Name": "Borgan"
  },
  {
    "First Name": "Dillon",
    "Last Name": "Boucher"
  },
  {
    "First Name": "Genevieve",
    "Last Name": "Bourdon"
  },
  {
    "First Name": "Sage",
    "Last Name": "Bowden"
  },
  {
    "First Name": "Rance",
    "Last Name": "Bowman"
  },
  {
    "First Name": "Landry",
    "Last Name": "Bramhall"
  },
  {
    "First Name": "Scarlett",
    "Last Name": "Branson"
  },
  {
    "First Name": "Charlotte",
    "Last Name": "Brauer"
  },
  {
    "First Name": "Christian",
    "Last Name": "Brodersen"
  },
  {
    "First Name": "McCarty",
    "Last Name": "Brooks"
  },
  {
    "First Name": "Harrison",
    "Last Name": "Brown"
  },
  {
    "First Name": "Matthew",
    "Last Name": "Brown"
  },
  {
    "First Name": "Blakely",
    "Last Name": "Burton"
  },
  {
    "First Name": "Teodora",
    "Last Name": "Bustos"
  },
  {
    "First Name": "Ruxia",
    "Last Name": "Cao"
  },
  {
    "First Name": "Morgan",
    "Last Name": "Cao-Hatch"
  },
  {
    "First Name": "Graham",
    "Last Name": "Caraballo"
  },
  {
    "First Name": "Preston",
    "Last Name": "Cardone"
  },
  {
    "First Name": "Vincent",
    "Last Name": "Carrizales"
  },
  {
    "First Name": "Pendleton",
    "Last Name": "Carson"
  },
  {
    "First Name": "Cole",
    "Last Name": "Castellanos"
  },
  {
    "First Name": "Harper",
    "Last Name": "Chalmers"
  },
  {
    "First Name": "Bennett",
    "Last Name": "Chan"
  },
  {
    "First Name": "Carter",
    "Last Name": "Chang"
  },
  {
    "First Name": "Leya",
    "Last Name": "Cheruku"
  },
  {
    "First Name": "Ella",
    "Last Name": "Childs"
  },
  {
    "First Name": "Edward",
    "Last Name": "Clark"
  },
  {
    "First Name": "James",
    "Last Name": "Clarke"
  },
  {
    "First Name": "Noah",
    "Last Name": "Clayton"
  },
  {
    "First Name": "Charlotte",
    "Last Name": "Cohen"
  },
  {
    "First Name": "Jackson",
    "Last Name": "Cohen"
  },
  {
    "First Name": "Nathaniel",
    "Last Name": "Cohen"
  },
  {
    "First Name": "Brody",
    "Last Name": "Coleman"
  },
  {
    "First Name": "Catherine",
    "Last Name": "Comeaux"
  },
  {
    "First Name": "Caroline",
    "Last Name": "Compton"
  },
  {
    "First Name": "Evalyn",
    "Last Name": "Conlan"
  },
  {
    "First Name": "Robert",
    "Last Name": "Corr"
  },
  {
    "First Name": "Amaya",
    "Last Name": "Cosme"
  },
  {
    "First Name": "Hampton",
    "Last Name": "Cox"
  },
  {
    "First Name": "James",
    "Last Name": "Cox"
  },
  {
    "First Name": "Annabelle",
    "Last Name": "Crawford"
  },
  {
    "First Name": "Lou",
    "Last Name": "Crawford"
  },
  {
    "First Name": "Landry",
    "Last Name": "Cristofoli"
  },
  {
    "First Name": "Connor",
    "Last Name": "Crouch"
  },
  {
    "First Name": "Cole",
    "Last Name": "Crow"
  },
  {
    "First Name": "Mary",
    "Last Name": "Crowley"
  },
  {
    "First Name": "Maxwell",
    "Last Name": "Danley"
  },
  {
    "First Name": "William",
    "Last Name": "DeArman"
  },
  {
    "First Name": "Juliet",
    "Last Name": "Denbow"
  },
  {
    "First Name": "Eleni",
    "Last Name": "Derksen"
  },
  {
    "First Name": "Victor",
    "Last Name": "DiBlasi"
  },
  {
    "First Name": "Isla",
    "Last Name": "DiCanio"
  },
  {
    "First Name": "Wynne",
    "Last Name": "Doffermyre"
  },
  {
    "First Name": "Maya",
    "Last Name": "Doncic"
  },
  {
    "First Name": "Isaac",
    "Last Name": "Droege"
  },
  {
    "First Name": "Margaret",
    "Last Name": "Drummond"
  },
  {
    "First Name": "Ellie",
    "Last Name": "Drysdale"
  },
  {
    "First Name": "David",
    "Last Name": "Dummer"
  },
  {
    "First Name": "Allan",
    "Last Name": "Dunlap"
  },
  {
    "First Name": "June",
    "Last Name": "Duplantis"
  },
  {
    "First Name": "William",
    "Last Name": "Durkee"
  },
  {
    "First Name": "Peter",
    "Last Name": "Dvorocsik"
  },
  {
    "First Name": "Perry",
    "Last Name": "Eastman"
  },
  {
    "First Name": "Victoria",
    "Last Name": "Echevarria"
  },
  {
    "First Name": "William",
    "Last Name": "Egan"
  },
  {
    "First Name": "Margot",
    "Last Name": "Elifson"
  },
  {
    "First Name": "Nolan",
    "Last Name": "Elliott"
  },
  {
    "First Name": "Everly",
    "Last Name": "Emerson"
  },
  {
    "First Name": "Larson",
    "Last Name": "Eppler"
  },
  {
    "First Name": "William",
    "Last Name": "Erman"
  },
  {
    "First Name": "Caleb",
    "Last Name": "Ernst"
  },
  {
    "First Name": "Paloma",
    "Last Name": "Escobar"
  },
  {
    "First Name": "Valentino",
    "Last Name": "Escobar"
  },
  {
    "First Name": "William",
    "Last Name": "Evans"
  },
  {
    "First Name": "Hudson",
    "Last Name": "Everett"
  },
  {
    "First Name": "Channing",
    "Last Name": "Falls"
  },
  {
    "First Name": "Jackson",
    "Last Name": "Feetham"
  },
  {
    "First Name": "Hannah",
    "Last Name": "Feldman"
  },
  {
    "First Name": "Bradley",
    "Last Name": "Ferguson"
  },
  {
    "First Name": "Weston",
    "Last Name": "Ferguson"
  },
  {
    "First Name": "Ford",
    "Last Name": "Fletcher"
  },
  {
    "First Name": "Sofia",
    "Last Name": "Forlino"
  },
  {
    "First Name": "Bowen",
    "Last Name": "Frantz"
  },
  {
    "First Name": "Lia",
    "Last Name": "Froimovici"
  },
  {
    "First Name": "Daniel",
    "Last Name": "Fuqua"
  },
  {
    "First Name": "Reagan",
    "Last Name": "Furr"
  },
  {
    "First Name": "Isaac",
    "Last Name": "Futerfas"
  },
  {
    "First Name": "Tate",
    "Last Name": "Gerhauser"
  },
  {
    "First Name": "Patrick",
    "Last Name": "Gibbs"
  },
  {
    "First Name": "Henry",
    "Last Name": "Gilbert"
  },
  {
    "First Name": "Adelaide",
    "Last Name": "Glover"
  },
  {
    "First Name": "Emilia",
    "Last Name": "Goldman"
  },
  {
    "First Name": "Pietra",
    "Last Name": "Gomes Resque"
  },
  {
    "First Name": "Rachel",
    "Last Name": "Gonzalez"
  },
  {
    "First Name": "Kennedy",
    "Last Name": "Grabowsky"
  },
  {
    "First Name": "Gavin",
    "Last Name": "Green"
  },
  {
    "First Name": "Madeline",
    "Last Name": "Green"
  },
  {
    "First Name": "Ryan",
    "Last Name": "Guerry"
  },
  {
    "First Name": "Audrey",
    "Last Name": "Guinn"
  },
  {
    "First Name": "Iris",
    "Last Name": "Haddock"
  },
  {
    "First Name": "Lucas",
    "Last Name": "Hage"
  },
  {
    "First Name": "Sienna",
    "Last Name": "Hajibashi"
  },
  {
    "First Name": "Hayes",
    "Last Name": "Hall"
  },
  {
    "First Name": "Hayden",
    "Last Name": "Hammel"
  },
  {
    "First Name": "Alexandria",
    "Last Name": "Hampton"
  },
  {
    "First Name": "Harper",
    "Last Name": "Hanna"
  },
  {
    "First Name": "Laurel",
    "Last Name": "Hanna"
  },
  {
    "First Name": "Jemma",
    "Last Name": "Hanson"
  },
  {
    "First Name": "Henry",
    "Last Name": "Harbison"
  },
  {
    "First Name": "Marshall",
    "Last Name": "Harding"
  },
  {
    "First Name": "Oliver",
    "Last Name": "Hawkins"
  },
  {
    "First Name": "Alan",
    "Last Name": "Haworth"
  },
  {
    "First Name": "Henry",
    "Last Name": "Hays"
  },
  {
    "First Name": "Steven",
    "Last Name": "He"
  },
  {
    "First Name": "William",
    "Last Name": "Head"
  },
  {
    "First Name": "Camden",
    "Last Name": "Heikenfeld"
  },
  {
    "First Name": "Liam",
    "Last Name": "Henderson"
  },
  {
    "First Name": "Lillian",
    "Last Name": "Henderson"
  },
  {
    "First Name": "Luke",
    "Last Name": "Henderson"
  },
  {
    "First Name": "Piper",
    "Last Name": "Henderson"
  },
  {
    "First Name": "Helena",
    "Last Name": "Hendrix"
  },
  {
    "First Name": "John",
    "Last Name": "Hensley"
  },
  {
    "First Name": "Thomas",
    "Last Name": "Hill"
  },
  {
    "First Name": "Hudson",
    "Last Name": "Hinds"
  },
  {
    "First Name": "Ava",
    "Last Name": "Hines"
  },
  {
    "First Name": "Howard",
    "Last Name": "Hines"
  },
  {
    "First Name": "Clark",
    "Last Name": "Hodges"
  },
  {
    "First Name": "Margaret",
    "Last Name": "Hodges"
  },
  {
    "First Name": "Jackson",
    "Last Name": "Hohertz"
  },
  {
    "First Name": "Emma",
    "Last Name": "Hollis"
  },
  {
    "First Name": "Reeve",
    "Last Name": "Honea"
  },
  {
    "First Name": "James",
    "Last Name": "Hopper"
  },
  {
    "First Name": "Dylan",
    "Last Name": "Horne"
  },
  {
    "First Name": "Anson",
    "Last Name": "Howe"
  },
  {
    "First Name": "Beckham",
    "Last Name": "Hufsey"
  },
  {
    "First Name": "Duke",
    "Last Name": "Humphrey"
  },
  {
    "First Name": "Ashley",
    "Last Name": "Hunt"
  },
  {
    "First Name": "John",
    "Last Name": "Hunt"
  },
  {
    "First Name": "Madison",
    "Last Name": "Hunt"
  },
  {
    "First Name": "Jonathan",
    "Last Name": "Ingram-Scoresby"
  },
  {
    "First Name": "Mia",
    "Last Name": "Isom"
  },
  {
    "First Name": "Eleanor",
    "Last Name": "Jackson"
  },
  {
    "First Name": "Francesca",
    "Last Name": "Jackson"
  },
  {
    "First Name": "John",
    "Last Name": "Jackson"
  },
  {
    "First Name": "Harlan",
    "Last Name": "Jago"
  },
  {
    "First Name": "Van",
    "Last Name": "Jaudes"
  },
  {
    "First Name": "Nolan",
    "Last Name": "Jeffers"
  },
  {
    "First Name": "Shelby",
    "Last Name": "Johns"
  },
  {
    "First Name": "Emily",
    "Last Name": "Johnson"
  },
  {
    "First Name": "Russell",
    "Last Name": "Johnson"
  },
  {
    "First Name": "Murray",
    "Last Name": "Jordan"
  },
  {
    "First Name": "Peninah",
    "Last Name": "Karr"
  },
  {
    "First Name": "Sahiba",
    "Last Name": "Kaur"
  },
  {
    "First Name": "Riley",
    "Last Name": "Keene"
  },
  {
    "First Name": "Symphony",
    "Last Name": "Kelly"
  },
  {
    "First Name": "Davis",
    "Last Name": "Kelton"
  },
  {
    "First Name": "Cali",
    "Last Name": "Kershaw"
  },
  {
    "First Name": "Daisy",
    "Last Name": "Kerstetter"
  },
  {
    "First Name": "Bradlee",
    "Last Name": "Kessler"
  },
  {
    "First Name": "Zorayz",
    "Last Name": "Khan"
  },
  {
    "First Name": "Neeyah",
    "Last Name": "Kheiri"
  },
  {
    "First Name": "James",
    "Last Name": "Kite"
  },
  {
    "First Name": "Margaret",
    "Last Name": "Kohler"
  },
  {
    "First Name": "Maya",
    "Last Name": "Kukekova"
  },
  {
    "First Name": "William",
    "Last Name": "Kwon"
  },
  {
    "First Name": "Margaret",
    "Last Name": "Langley"
  },
  {
    "First Name": "Elizabeth",
    "Last Name": "Latham"
  },
  {
    "First Name": "Grant",
    "Last Name": "Latham"
  },
  {
    "First Name": "Mackenzie",
    "Last Name": "Lawlis"
  },
  {
    "First Name": "Sam",
    "Last Name": "Leake"
  },
  {
    "First Name": "Stokes",
    "Last Name": "Leckband"
  },
  {
    "First Name": "Brielle",
    "Last Name": "Ledford"
  },
  {
    "First Name": "Elizabeth",
    "Last Name": "Lee"
  },
  {
    "First Name": "Owen",
    "Last Name": "Lee"
  },
  {
    "First Name": "Sienna",
    "Last Name": "Lee"
  },
  {
    "First Name": "Vivienne",
    "Last Name": "Lee"
  },
  {
    "First Name": "Eloise",
    "Last Name": "Lehman"
  },
  {
    "First Name": "Sullivan",
    "Last Name": "Lester"
  },
  {
    "First Name": "James",
    "Last Name": "Lewis"
  },
  {
    "First Name": "William",
    "Last Name": "Lewis"
  },
  {
    "First Name": "Siyan",
    "Last Name": "Li"
  },
  {
    "First Name": "Jayden",
    "Last Name": "Lin"
  },
  {
    "First Name": "James",
    "Last Name": "Litchfield"
  },
  {
    "First Name": "Addyson",
    "Last Name": "Liu"
  },
  {
    "First Name": "Charles",
    "Last Name": "Longo"
  },
  {
    "First Name": "Mason",
    "Last Name": "Lu"
  },
  {
    "First Name": "Zachary",
    "Last Name": "Luu"
  },
  {
    "First Name": "Mason",
    "Last Name": "Lynch"
  },
  {
    "First Name": "Marilyn",
    "Last Name": "Macatee"
  },
  {
    "First Name": "Olivia",
    "Last Name": "Magadan Riise"
  },
  {
    "First Name": "Josephine",
    "Last Name": "Malaise"
  },
  {
    "First Name": "Winifred",
    "Last Name": "Malone"
  },
  {
    "First Name": "Anthony",
    "Last Name": "Manakides"
  },
  {
    "First Name": "Lainey",
    "Last Name": "Marshall"
  },
  {
    "First Name": "Hannah",
    "Last Name": "Marx"
  },
  {
    "First Name": "Isabella",
    "Last Name": "Mathew"
  },
  {
    "First Name": "John",
    "Last Name": "Maxwell"
  },
  {
    "First Name": "Wyatt",
    "Last Name": "Mayberry"
  },
  {
    "First Name": "Emilie",
    "Last Name": "McCallan"
  },
  {
    "First Name": "Tahlia",
    "Last Name": "McCawley"
  },
  {
    "First Name": "Kathryn",
    "Last Name": "McDonough"
  },
  {
    "First Name": "Pearl",
    "Last Name": "McDonough"
  },
  {
    "First Name": "Wesley",
    "Last Name": "McKnight"
  },
  {
    "First Name": "Elisabeth",
    "Last Name": "McWilliams"
  },
  {
    "First Name": "Maximilenne",
    "Last Name": "Medrano"
  },
  {
    "First Name": "Macon",
    "Last Name": "Messer"
  },
  {
    "First Name": "Sloan",
    "Last Name": "Messina"
  },
  {
    "First Name": "Luke",
    "Last Name": "Metzler"
  },
  {
    "First Name": "Walter",
    "Last Name": "Meyer"
  },
  {
    "First Name": "Major",
    "Last Name": "Michelson"
  },
  {
    "First Name": "Beckett",
    "Last Name": "Miller"
  },
  {
    "First Name": "Alec",
    "Last Name": "Minasoff"
  },
  {
    "First Name": "Alexander",
    "Last Name": "Mitchell"
  },
  {
    "First Name": "Wynne",
    "Last Name": "Mitchell"
  },
  {
    "First Name": "Shaylee",
    "Last Name": "Modha"
  },
  {
    "First Name": "Luke",
    "Last Name": "Monroe"
  },
  {
    "First Name": "Jonathan",
    "Last Name": "Moore"
  },
  {
    "First Name": "Myles",
    "Last Name": "Morgan"
  },
  {
    "First Name": "Greyson",
    "Last Name": "Morin"
  },
  {
    "First Name": "Maxwell",
    "Last Name": "Morski"
  },
  {
    "First Name": "Jude",
    "Last Name": "Mudigere"
  },
  {
    "First Name": "Noah",
    "Last Name": "Mudigere"
  },
  {
    "First Name": "Mila",
    "Last Name": "Mugavero"
  },
  {
    "First Name": "Evelyn",
    "Last Name": "Murrell"
  },
  {
    "First Name": "Alexandra",
    "Last Name": "Musselman"
  },
  {
    "First Name": "Lila",
    "Last Name": "Musselman"
  },
  {
    "First Name": "Andersen",
    "Last Name": "Myatt"
  },
  {
    "First Name": "Oliver",
    "Last Name": "Naggar"
  },
  {
    "First Name": "Harper",
    "Last Name": "Navarre"
  },
  {
    "First Name": "Holland",
    "Last Name": "Newsome"
  },
  {
    "First Name": "Colette",
    "Last Name": "Nicholson"
  },
  {
    "First Name": "Lillian",
    "Last Name": "Nierling"
  },
  {
    "First Name": "Morton",
    "Last Name": "Nixon"
  },
  {
    "First Name": "Nicholas",
    "Last Name": "Nowak"
  },
  {
    "First Name": "Brian",
    "Last Name": "OBoyle"
  },
  {
    "First Name": "Ava",
    "Last Name": "Ocker"
  },
  {
    "First Name": "James",
    "Last Name": "Ocker"
  },
  {
    "First Name": "William",
    "Last Name": "Ohlenburg"
  },
  {
    "First Name": "Nola",
    "Last Name": "Olsen"
  },
  {
    "First Name": "James",
    "Last Name": "Olson"
  },
  {
    "First Name": "Vivienne",
    "Last Name": "Oneacre"
  },
  {
    "First Name": "Ansel",
    "Last Name": "Ortiz"
  },
  {
    "First Name": "Rodrigo",
    "Last Name": "Orvananos Cardenas"
  },
  {
    "First Name": "Olive",
    "Last Name": "Overton"
  },
  {
    "First Name": "Vivian",
    "Last Name": "Overton"
  },
  {
    "First Name": "Maddox",
    "Last Name": "Owen"
  },
  {
    "First Name": "Tanner",
    "Last Name": "Ozkaya"
  },
  {
    "First Name": "Daniella",
    "Last Name": "Ozsan"
  },
  {
    "First Name": "Robert",
    "Last Name": "Palmer"
  },
  {
    "First Name": "Shakti",
    "Last Name": "Pandit"
  },
  {
    "First Name": "Annabelle",
    "Last Name": "Parecki"
  },
  {
    "First Name": "Kareena",
    "Last Name": "Parikh"
  },
  {
    "First Name": "Mason",
    "Last Name": "Park"
  },
  {
    "First Name": "Savannah",
    "Last Name": "Passmore"
  },
  {
    "First Name": "Reese",
    "Last Name": "Patten"
  },
  {
    "First Name": "Conrad",
    "Last Name": "Patterson"
  },
  {
    "First Name": "Oliver",
    "Last Name": "Peck"
  },
  {
    "First Name": "Paige",
    "Last Name": "Pennington"
  },
  {
    "First Name": "Mayrin",
    "Last Name": "Perez"
  },
  {
    "First Name": "Merritt",
    "Last Name": "Petka"
  },
  {
    "First Name": "Nolan",
    "Last Name": "Petrone"
  },
  {
    "First Name": "Ava",
    "Last Name": "Pfirrmann"
  },
  {
    "First Name": "Blair",
    "Last Name": "Phillips"
  },
  {
    "First Name": "Holly",
    "Last Name": "Phillips"
  },
  {
    "First Name": "Victoria",
    "Last Name": "Phillips"
  },
  {
    "First Name": "Mary Katherine",
    "Last Name": "Porter"
  },
  {
    "First Name": "Hayley",
    "Last Name": "Price"
  },
  {
    "First Name": "Hayes",
    "Last Name": "Prine"
  },
  {
    "First Name": "Jolie",
    "Last Name": "Pruett"
  },
  {
    "First Name": "Emma",
    "Last Name": "Purcell"
  },
  {
    "First Name": "Kate",
    "Last Name": "Purcell"
  },
  {
    "First Name": "Finn",
    "Last Name": "Purvis"
  },
  {
    "First Name": "Camila",
    "Last Name": "Quiroz Graham"
  },
  {
    "First Name": "Oliver",
    "Last Name": "Radel"
  },
  {
    "First Name": "Claire",
    "Last Name": "Rae"
  },
  {
    "First Name": "Maxwell",
    "Last Name": "Ramundt"
  },
  {
    "First Name": "Anna",
    "Last Name": "Ratliff"
  },
  {
    "First Name": "Mary",
    "Last Name": "Ratliff"
  },
  {
    "First Name": "Riggs",
    "Last Name": "Recker"
  },
  {
    "First Name": "Ryder",
    "Last Name": "Redgrave"
  },
  {
    "First Name": "Emily",
    "Last Name": "Reed"
  },
  {
    "First Name": "Max",
    "Last Name": "Reed"
  },
  {
    "First Name": "Eliza",
    "Last Name": "Reis"
  },
  {
    "First Name": "Nathaniel",
    "Last Name": "Reyes"
  },
  {
    "First Name": "Paxton",
    "Last Name": "Riter"
  },
  {
    "First Name": "Caroline",
    "Last Name": "Roach"
  },
  {
    "First Name": "Reese",
    "Last Name": "Robbins"
  },
  {
    "First Name": "Ace",
    "Last Name": "Roberts"
  },
  {
    "First Name": "Mary",
    "Last Name": "Roberts"
  },
  {
    "First Name": "Elda",
    "Last Name": "Robertson"
  },
  {
    "First Name": "MARGARET",
    "Last Name": "ROBINIUS"
  },
  {
    "First Name": "Lauren",
    "Last Name": "Rockwood"
  },
  {
    "First Name": "Gloria",
    "Last Name": "Rolls"
  },
  {
    "First Name": "Miller",
    "Last Name": "Rosen"
  },
  {
    "First Name": "Arthur",
    "Last Name": "Roslund"
  },
  {
    "First Name": "Catherine",
    "Last Name": "Roy"
  },
  {
    "First Name": "Samuel",
    "Last Name": "Sachse"
  },
  {
    "First Name": "Charles",
    "Last Name": "Samler"
  },
  {
    "First Name": "Violeta",
    "Last Name": "Sanchez-Melgarejo"
  },
  {
    "First Name": "Ross",
    "Last Name": "Santa Maria"
  },
  {
    "First Name": "Jeffery",
    "Last Name": "Scarff"
  },
  {
    "First Name": "Henry",
    "Last Name": "Schimmels"
  },
  {
    "First Name": "Emerlyn",
    "Last Name": "Schram"
  },
  {
    "First Name": "Grace",
    "Last Name": "Schroeder"
  },
  {
    "First Name": "Robert",
    "Last Name": "Schultis"
  },
  {
    "First Name": "Price",
    "Last Name": "Sears"
  },
  {
    "First Name": "Hannah",
    "Last Name": "Settle"
  },
  {
    "First Name": "Dylan",
    "Last Name": "Shadle"
  },
  {
    "First Name": "Praveen",
    "Last Name": "Shakkottai"
  },
  {
    "First Name": "Alexandra",
    "Last Name": "Shaw"
  },
  {
    "First Name": "James",
    "Last Name": "Shelton"
  },
  {
    "First Name": "Ruth",
    "Last Name": "Shores"
  },
  {
    "First Name": "Valentina",
    "Last Name": "Short"
  },
  {
    "First Name": "Collier",
    "Last Name": "Shuart"
  },
  {
    "First Name": "Parker",
    "Last Name": "Sibert"
  },
  {
    "First Name": "Levi",
    "Last Name": "Siegel"
  },
  {
    "First Name": "Tessa",
    "Last Name": "Singleton"
  },
  {
    "First Name": "Evelyn",
    "Last Name": "Slaven"
  },
  {
    "First Name": "Campbell",
    "Last Name": "Smetko"
  },
  {
    "First Name": "Elvin",
    "Last Name": "Smith"
  },
  {
    "First Name": "Robert",
    "Last Name": "Smith"
  },
  {
    "First Name": "Vivian",
    "Last Name": "Smith"
  },
  {
    "First Name": "River",
    "Last Name": "Snyder"
  },
  {
    "First Name": "Clara",
    "Last Name": "Sorenson"
  },
  {
    "First Name": "Wilson",
    "Last Name": "Spears"
  },
  {
    "First Name": "John",
    "Last Name": "Sporich"
  },
  {
    "First Name": "Finley",
    "Last Name": "Stabler"
  },
  {
    "First Name": "Stratton",
    "Last Name": "Stensrud"
  },
  {
    "First Name": "William",
    "Last Name": "Strickland"
  },
  {
    "First Name": "Hayes",
    "Last Name": "Strohbehn"
  },
  {
    "First Name": "William",
    "Last Name": "Studenko"
  },
  {
    "First Name": "John",
    "Last Name": "Stull"
  },
  {
    "First Name": "Hunter",
    "Last Name": "Sturdevant"
  },
  {
    "First Name": "Liam",
    "Last Name": "Sultan"
  },
  {
    "First Name": "Lleyton",
    "Last Name": "Sumner"
  },
  {
    "First Name": "Xuke",
    "Last Name": "Sun"
  },
  {
    "First Name": "Olivia",
    "Last Name": "Sutton"
  },
  {
    "First Name": "Ella",
    "Last Name": "Swail"
  },
  {
    "First Name": "Amelia",
    "Last Name": "Talbott"
  },
  {
    "First Name": "Penelope",
    "Last Name": "Tanner"
  },
  {
    "First Name": "Vika",
    "Last Name": "Tauscher"
  },
  {
    "First Name": "Henry",
    "Last Name": "Taylor"
  },
  {
    "First Name": "Makena",
    "Last Name": "Teeples"
  },
  {
    "First Name": "Gevorg",
    "Last Name": "Ter-Papian"
  },
  {
    "First Name": "Lara",
    "Last Name": "Terry"
  },
  {
    "First Name": "Andrew",
    "Last Name": "Thomas"
  },
  {
    "First Name": "Flynn",
    "Last Name": "Thomas"
  },
  {
    "First Name": "Jane",
    "Last Name": "Thomas"
  },
  {
    "First Name": "Eli",
    "Last Name": "Tinkle"
  },
  {
    "First Name": "Austin",
    "Last Name": "Tobin"
  },
  {
    "First Name": "William",
    "Last Name": "Toce"
  },
  {
    "First Name": "Weston",
    "Last Name": "Tomsula"
  },
  {
    "First Name": "Campbell",
    "Last Name": "Tovo"
  },
  {
    "First Name": "Margaret",
    "Last Name": "Treaster"
  },
  {
    "First Name": "Jacquelyn",
    "Last Name": "Trowbridge"
  },
  {
    "First Name": "Emily",
    "Last Name": "Trulock"
  },
  {
    "First Name": "Nina",
    "Last Name": "Turney"
  },
  {
    "First Name": "Nora",
    "Last Name": "Turney"
  },
  {
    "First Name": "James",
    "Last Name": "Turpin"
  },
  {
    "First Name": "Charles",
    "Last Name": "Underwood"
  },
  {
    "First Name": "ANNIE",
    "Last Name": "VAHRENKAMP"
  },
  {
    "First Name": "BLAKELY",
    "Last Name": "VAHRENKAMP"
  },
  {
    "First Name": "Mila",
    "Last Name": "Vahrenkamp"
  },
  {
    "First Name": "Noelle",
    "Last Name": "Vainshel"
  },
  {
    "First Name": "Lucas",
    "Last Name": "Vandervinne"
  },
  {
    "First Name": "Ava",
    "Last Name": "Venable"
  },
  {
    "First Name": "Victor",
    "Last Name": "Von Horvath"
  },
  {
    "First Name": "Lilly",
    "Last Name": "Wagoner"
  },
  {
    "First Name": "Lillian",
    "Last Name": "Walden"
  },
  {
    "First Name": "Thomas",
    "Last Name": "Walden"
  },
  {
    "First Name": "Sarah",
    "Last Name": "Walder"
  },
  {
    "First Name": "Samuel",
    "Last Name": "Wall"
  },
  {
    "First Name": "Anne",
    "Last Name": "Wallace"
  },
  {
    "First Name": "Lauriane",
    "Last Name": "Wallis"
  },
  {
    "First Name": "Ryan",
    "Last Name": "Wang"
  },
  {
    "First Name": "Reese",
    "Last Name": "Ward"
  },
  {
    "First Name": "Mikaeel",
    "Last Name": "Warnakulasuriya"
  },
  {
    "First Name": "Xander",
    "Last Name": "Warnakulasuriya"
  },
  {
    "First Name": "Jacob",
    "Last Name": "Waters"
  },
  {
    "First Name": "Cullen",
    "Last Name": "Wegman"
  },
  {
    "First Name": "Harper",
    "Last Name": "Weinand"
  },
  {
    "First Name": "Holden",
    "Last Name": "Weinand"
  },
  {
    "First Name": "Margot",
    "Last Name": "Weinstein"
  },
  {
    "First Name": "Mary",
    "Last Name": "White"
  },
  {
    "First Name": "Kendall",
    "Last Name": "Widmer"
  },
  {
    "First Name": "Britton",
    "Last Name": "Wilhite"
  },
  {
    "First Name": "Kate",
    "Last Name": "Williams"
  },
  {
    "First Name": "Cooper",
    "Last Name": "Wilson"
  },
  {
    "First Name": "Elizabeth",
    "Last Name": "Wilson"
  },
  {
    "First Name": "Luke",
    "Last Name": "Winner"
  },
  {
    "First Name": "Elan",
    "Last Name": "Winski"
  },
  {
    "First Name": "Clara",
    "Last Name": "Woldert"
  },
  {
    "First Name": "Shirley",
    "Last Name": "Wortley"
  },
  {
    "First Name": "Cooper",
    "Last Name": "Wu"
  },
  {
    "First Name": "Cashel",
    "Last Name": "Wurzbach"
  },
  {
    "First Name": "Reza",
    "Last Name": "Wyatt"
  },
  {
    "First Name": "Newman",
    "Last Name": "Xie"
  },
  {
    "First Name": "Kevin",
    "Last Name": "Xu"
  },
  {
    "First Name": "Talha",
    "Last Name": "Yaradanakul"
  },
  {
    "First Name": "Madeleine",
    "Last Name": "Yoakam"
  },
  {
    "First Name": "William",
    "Last Name": "Zapffe"
  },
  {
    "First Name": "Elizabeth",
    "Last Name": "Zhan"
  },
  {
    "First Name": "Harper",
    "Last Name": "Zielke"
  },
  {
    "First Name": "Jude",
    "Last Name": "Abelmann"
  },
  {
    "First Name": "Gabriel",
    "Last Name": "Ackerman"
  },
  {
    "First Name": "Olivia",
    "Last Name": "Adams"
  },
  {
    "First Name": "Michael",
    "Last Name": "Addison"
  },
  {
    "First Name": "Abigail",
    "Last Name": "Aldrich"
  },
  {
    "First Name": "Ketana",
    "Last Name": "Andersen"
  },
  {
    "First Name": "Saylor",
    "Last Name": "Anderson"
  },
  {
    "First Name": "Anna",
    "Last Name": "Apple"
  },
  {
    "First Name": "McGuire",
    "Last Name": "Armstrong"
  },
  {
    "First Name": "Simran",
    "Last Name": "Arora"
  },
  {
    "First Name": "Pierce",
    "Last Name": "Ascenzo"
  },
  {
    "First Name": "John",
    "Last Name": "Baird"
  },
  {
    "First Name": "Claire",
    "Last Name": "Baldwin"
  },
  {
    "First Name": "Caroline",
    "Last Name": "Ballard"
  },
  {
    "First Name": "Austin",
    "Last Name": "Bame"
  },
  {
    "First Name": "Samuel",
    "Last Name": "Bandlamudi"
  },
  {
    "First Name": "Eliza",
    "Last Name": "Barber"
  },
  {
    "First Name": "Emma",
    "Last Name": "Barner"
  },
  {
    "First Name": "James",
    "Last Name": "Barnes"
  },
  {
    "First Name": "Clardy",
    "Last Name": "Barnett"
  },
  {
    "First Name": "Robert",
    "Last Name": "Barnett"
  },
  {
    "First Name": "Julian",
    "Last Name": "Barsotti"
  },
  {
    "First Name": "Emory",
    "Last Name": "Baskett"
  },
  {
    "First Name": "Alyssa",
    "Last Name": "Baskin"
  },
  {
    "First Name": "Lillian",
    "Last Name": "Beakley"
  },
  {
    "First Name": "Elizabeth",
    "Last Name": "Beale"
  },
  {
    "First Name": "Erin",
    "Last Name": "Beck"
  },
  {
    "First Name": "Brady",
    "Last Name": "Becker"
  },
  {
    "First Name": "Sophie",
    "Last Name": "Becker"
  },
  {
    "First Name": "Margot",
    "Last Name": "Begert"
  },
  {
    "First Name": "Helen",
    "Last Name": "Bell"
  },
  {
    "First Name": "Hollis",
    "Last Name": "Bennett"
  },
  {
    "First Name": "Elizabeth",
    "Last Name": "Berlin"
  },
  {
    "First Name": "Kyle",
    "Last Name": "Blechschmidt"
  },
  {
    "First Name": "Philip",
    "Last Name": "Boles"
  },
  {
    "First Name": "Kate",
    "Last Name": "Bolton"
  },
  {
    "First Name": "Madeline",
    "Last Name": "Boucher"
  },
  {
    "First Name": "John",
    "Last Name": "Bowen"
  },
  {
    "First Name": "Sarah",
    "Last Name": "Bowen"
  },
  {
    "First Name": "Stella",
    "Last Name": "Bowen"
  },
  {
    "First Name": "Lloyd",
    "Last Name": "Bowles"
  },
  {
    "First Name": "Ruffin",
    "Last Name": "Boyett"
  },
  {
    "First Name": "Henry",
    "Last Name": "Boynton"
  },
  {
    "First Name": "Oliver",
    "Last Name": "Bradbury"
  },
  {
    "First Name": "Jude",
    "Last Name": "Bridges"
  },
  {
    "First Name": "Nolia",
    "Last Name": "Bright"
  },
  {
    "First Name": "William",
    "Last Name": "Brodersen"
  },
  {
    "First Name": "Christian",
    "Last Name": "Brook"
  },
  {
    "First Name": "Cooper",
    "Last Name": "Brown"
  },
  {
    "First Name": "Jacqueline",
    "Last Name": "Brown"
  },
  {
    "First Name": "Reid",
    "Last Name": "Brown"
  },
  {
    "First Name": "Robert",
    "Last Name": "Brown"
  },
  {
    "First Name": "Shawn",
    "Last Name": "Brumit"
  },
  {
    "First Name": "Lillian",
    "Last Name": "Bryant"
  },
  {
    "First Name": "Reid",
    "Last Name": "Bryant"
  },
  {
    "First Name": "Case",
    "Last Name": "Buis"
  },
  {
    "First Name": "Langley",
    "Last Name": "Burns"
  },
  {
    "First Name": "Michael",
    "Last Name": "Byrd"
  },
  {
    "First Name": "Kate",
    "Last Name": "Callahan"
  },
  {
    "First Name": "Colette",
    "Last Name": "Campbell"
  },
  {
    "First Name": "Laith",
    "Last Name": "Campbell"
  },
  {
    "First Name": "Carrie",
    "Last Name": "Carpenter"
  },
  {
    "First Name": "Blake",
    "Last Name": "Casey"
  },
  {
    "First Name": "Samantha",
    "Last Name": "Chandler"
  },
  {
    "First Name": "Hazel",
    "Last Name": "Chavoya"
  },
  {
    "First Name": "Lukas",
    "Last Name": "Cherkassky"
  },
  {
    "First Name": "John",
    "Last Name": "Clifton"
  },
  {
    "First Name": "Barrett",
    "Last Name": "Cobb"
  },
  {
    "First Name": "Mary",
    "Last Name": "Cochran"
  },
  {
    "First Name": "Rhys",
    "Last Name": "Colenso"
  },
  {
    "First Name": "Zoie",
    "Last Name": "Comeau"
  },
  {
    "First Name": "Emma",
    "Last Name": "Conroy"
  },
  {
    "First Name": "Ellis",
    "Last Name": "Coots"
  },
  {
    "First Name": "Virginia",
    "Last Name": "Cosgrove"
  },
  {
    "First Name": "Florence",
    "Last Name": "Cox"
  },
  {
    "First Name": "Alice",
    "Last Name": "Crain"
  },
  {
    "First Name": "Grace",
    "Last Name": "Crain"
  },
  {
    "First Name": "Frances",
    "Last Name": "Craine"
  },
  {
    "First Name": "Thomas",
    "Last Name": "Crawford"
  },
  {
    "First Name": "William",
    "Last Name": "Crawford"
  },
  {
    "First Name": "Navia",
    "Last Name": "Croom"
  },
  {
    "First Name": "Angelina",
    "Last Name": "Crosby"
  },
  {
    "First Name": "Trevor",
    "Last Name": "Crosby"
  },
  {
    "First Name": "Eleanor",
    "Last Name": "Curtin"
  },
  {
    "First Name": "Donald",
    "Last Name": "Dafoe"
  },
  {
    "First Name": "Tessa",
    "Last Name": "Dai"
  },
  {
    "First Name": "Lydia",
    "Last Name": "Dao"
  },
  {
    "First Name": "Andrew",
    "Last Name": "Davis"
  },
  {
    "First Name": "Gunnar",
    "Last Name": "Davis"
  },
  {
    "First Name": "Sahren",
    "Last Name": "Dayalji"
  },
  {
    "First Name": "Anna",
    "Last Name": "Dethlefsen"
  },
  {
    "First Name": "Cullen",
    "Last Name": "Dickey"
  },
  {
    "First Name": "Emma",
    "Last Name": "Diehl"
  },
  {
    "First Name": "Jackson",
    "Last Name": "Dixon"
  },
  {
    "First Name": "Genevieve",
    "Last Name": "Doak"
  },
  {
    "First Name": "Tully",
    "Last Name": "Donaldson"
  },
  {
    "First Name": "Clara",
    "Last Name": "Donohoe"
  },
  {
    "First Name": "William",
    "Last Name": "Doramus"
  },
  {
    "First Name": "Moira",
    "Last Name": "Doyle"
  },
  {
    "First Name": "Estelle",
    "Last Name": "Drennan"
  },
  {
    "First Name": "Shengming",
    "Last Name": "Du"
  },
  {
    "First Name": "Michael",
    "Last Name": "Duff"
  },
  {
    "First Name": "William",
    "Last Name": "Dunn"
  },
  {
    "First Name": "Fulton",
    "Last Name": "Edison"
  },
  {
    "First Name": "Angus",
    "Last Name": "Edwards"
  },
  {
    "First Name": "Caroline",
    "Last Name": "Elifson"
  },
  {
    "First Name": "Norah",
    "Last Name": "Ellis"
  },
  {
    "First Name": "Molly",
    "Last Name": "Elsener"
  },
  {
    "First Name": "Ashlyn",
    "Last Name": "Erickson"
  },
  {
    "First Name": "Peyton",
    "Last Name": "Erickson"
  },
  {
    "First Name": "Katherine",
    "Last Name": "Evans"
  },
  {
    "First Name": "Caffey",
    "Last Name": "Ewing"
  },
  {
    "First Name": "William",
    "Last Name": "Fairchild"
  },
  {
    "First Name": "Bennet",
    "Last Name": "Fasano"
  },
  {
    "First Name": "Sebastian",
    "Last Name": "Faulk"
  },
  {
    "First Name": "Grace",
    "Last Name": "Feeney"
  },
  {
    "First Name": "Elliot",
    "Last Name": "Feinstein"
  },
  {
    "First Name": "Ayla",
    "Last Name": "Ferdows"
  },
  {
    "First Name": "Colin",
    "Last Name": "Fetter"
  },
  {
    "First Name": "Arden",
    "Last Name": "Fitzenhagen"
  },
  {
    "First Name": "Henry",
    "Last Name": "Fitzgerald"
  },
  {
    "First Name": "Rory",
    "Last Name": "Flanagan"
  },
  {
    "First Name": "Henry",
    "Last Name": "Floyd"
  },
  {
    "First Name": "Sarah",
    "Last Name": "Francis"
  },
  {
    "First Name": "Brinley",
    "Last Name": "Frank"
  },
  {
    "First Name": "Waverly",
    "Last Name": "Frederick"
  },
  {
    "First Name": "Yardley",
    "Last Name": "Frederick"
  },
  {
    "First Name": "Claire",
    "Last Name": "Fredston"
  },
  {
    "First Name": "Allie",
    "Last Name": "Frierson"
  },
  {
    "First Name": "Paul",
    "Last Name": "Frotten"
  },
  {
    "First Name": "Yardley",
    "Last Name": "Fuge"
  },
  {
    "First Name": "Emma",
    "Last Name": "Fullam"
  },
  {
    "First Name": "Preston",
    "Last Name": "Gaebe"
  },
  {
    "First Name": "William",
    "Last Name": "Gaebe"
  },
  {
    "First Name": "Bo",
    "Last Name": "Gardner"
  },
  {
    "First Name": "Milo",
    "Last Name": "Garner"
  },
  {
    "First Name": "Samuel",
    "Last Name": "Gerard"
  },
  {
    "First Name": "Nolan",
    "Last Name": "Gerken"
  },
  {
    "First Name": "Isabel",
    "Last Name": "Ghillione"
  },
  {
    "First Name": "Asha",
    "Last Name": "Gill"
  },
  {
    "First Name": "Alexandra",
    "Last Name": "Glassman"
  },
  {
    "First Name": "Gage",
    "Last Name": "Gleaton"
  },
  {
    "First Name": "Joseph",
    "Last Name": "Goldman"
  },
  {
    "First Name": "Tynsley",
    "Last Name": "Goline"
  },
  {
    "First Name": "Davis",
    "Last Name": "Graber"
  },
  {
    "First Name": "Georgia",
    "Last Name": "Graham"
  },
  {
    "First Name": "Brooks",
    "Last Name": "Grasso"
  },
  {
    "First Name": "Hunter",
    "Last Name": "Green"
  },
  {
    "First Name": "Georgia",
    "Last Name": "Greth"
  },
  {
    "First Name": "Calvin",
    "Last Name": "Gruber"
  },
  {
    "First Name": "Estelle",
    "Last Name": "Guay"
  },
  {
    "First Name": "Luke",
    "Last Name": "Gurganus"
  },
  {
    "First Name": "Avery",
    "Last Name": "Gustafson"
  },
  {
    "First Name": "Jane",
    "Last Name": "Haig"
  },
  {
    "First Name": "Jackson",
    "Last Name": "Hall"
  },
  {
    "First Name": "Marie",
    "Last Name": "Hall"
  },
  {
    "First Name": "Sofia",
    "Last Name": "Hallam"
  },
  {
    "First Name": "Daniel",
    "Last Name": "Hamilton"
  },
  {
    "First Name": "Mary",
    "Last Name": "Hamilton"
  },
  {
    "First Name": "Jack",
    "Last Name": "Hammes"
  },
  {
    "First Name": "Helen",
    "Last Name": "Hanna"
  },
  {
    "First Name": "Sawyer",
    "Last Name": "Harmeling"
  },
  {
    "First Name": "Vivian",
    "Last Name": "Harmon"
  },
  {
    "First Name": "Davis",
    "Last Name": "Harper"
  },
  {
    "First Name": "Field",
    "Last Name": "Harrison"
  },
  {
    "First Name": "Kees",
    "Last Name": "Harvey"
  },
  {
    "First Name": "Preston",
    "Last Name": "Harvey"
  },
  {
    "First Name": "Louis",
    "Last Name": "He"
  },
  {
    "First Name": "Jack",
    "Last Name": "Healy"
  },
  {
    "First Name": "Harper",
    "Last Name": "Hefner"
  },
  {
    "First Name": "Luke",
    "Last Name": "Hefton"
  },
  {
    "First Name": "Peter",
    "Last Name": "Hefty"
  },
  {
    "First Name": "Audrey",
    "Last Name": "Hein"
  },
  {
    "First Name": "Ella",
    "Last Name": "Hendrix"
  },
  {
    "First Name": "Andrew",
    "Last Name": "Henry"
  },
  {
    "First Name": "Ricardo",
    "Last Name": "Hernandez"
  },
  {
    "First Name": "Sebastian",
    "Last Name": "Hernandez"
  },
  {
    "First Name": "Hayes",
    "Last Name": "Herold"
  },
  {
    "First Name": "Shelby",
    "Last Name": "Herren"
  },
  {
    "First Name": "Eloise",
    "Last Name": "Hicks"
  },
  {
    "First Name": "Isabella",
    "Last Name": "Hicks"
  },
  {
    "First Name": "Jet",
    "Last Name": "Hicks"
  },
  {
    "First Name": "Robert",
    "Last Name": "Higginbottom"
  },
  {
    "First Name": "Harrison",
    "Last Name": "Higgins"
  },
  {
    "First Name": "Jackson",
    "Last Name": "Higgins"
  },
  {
    "First Name": "Harrison",
    "Last Name": "Hill"
  },
  {
    "First Name": "Jeremy",
    "Last Name": "Ho"
  },
  {
    "First Name": "Alex",
    "Last Name": "Hoang"
  },
  {
    "First Name": "Henley",
    "Last Name": "Hodges"
  },
  {
    "First Name": "Smith",
    "Last Name": "Hoffmann"
  },
  {
    "First Name": "Eric",
    "Last Name": "Holcombe"
  },
  {
    "First Name": "Scarlett",
    "Last Name": "Horne"
  },
  {
    "First Name": "Leo",
    "Last Name": "Hsu"
  },
  {
    "First Name": "Kelly",
    "Last Name": "Hunt"
  },
  {
    "First Name": "Vivienne",
    "Last Name": "Hunt"
  },
  {
    "First Name": "Sloane",
    "Last Name": "Inabnett"
  },
  {
    "First Name": "Robert",
    "Last Name": "Inman"
  },
  {
    "First Name": "Walter",
    "Last Name": "Innamorati"
  },
  {
    "First Name": "Patrick",
    "Last Name": "Jackson"
  },
  {
    "First Name": "Thomas",
    "Last Name": "Jacob"
  },
  {
    "First Name": "Lynley",
    "Last Name": "Johnson"
  },
  {
    "First Name": "Sloan",
    "Last Name": "Johnson"
  },
  {
    "First Name": "Luke",
    "Last Name": "Johnston"
  },
  {
    "First Name": "Eden",
    "Last Name": "Jones"
  },
  {
    "First Name": "James",
    "Last Name": "Jones"
  },
  {
    "First Name": "William Griffin",
    "Last Name": "Jones"
  },
  {
    "First Name": "Ryan",
    "Last Name": "Judge"
  },
  {
    "First Name": "Eleanor",
    "Last Name": "Kalescky"
  },
  {
    "First Name": "Avani",
    "Last Name": "Kandel"
  },
  {
    "First Name": "Aashi",
    "Last Name": "Karamchandani"
  },
  {
    "First Name": "Beckham",
    "Last Name": "Kearney"
  },
  {
    "First Name": "Andrew",
    "Last Name": "Kelley"
  },
  {
    "First Name": "Wilde",
    "Last Name": "Kellstrom"
  },
  {
    "First Name": "Monroe",
    "Last Name": "Kennedy"
  },
  {
    "First Name": "Anna",
    "Last Name": "Khai"
  },
  {
    "First Name": "Hugh",
    "Last Name": "Knake"
  },
  {
    "First Name": "Emory",
    "Last Name": "Knobler"
  },
  {
    "First Name": "Shelton",
    "Last Name": "Kobler"
  },
  {
    "First Name": "Philipp",
    "Last Name": "Kormilitsin"
  },
  {
    "First Name": "Valia",
    "Last Name": "Kostadinova"
  },
  {
    "First Name": "Charles",
    "Last Name": "Krist"
  },
  {
    "First Name": "Jackson",
    "Last Name": "Kruppa"
  },
  {
    "First Name": "John",
    "Last Name": "Kuykendall"
  },
  {
    "First Name": "Emme",
    "Last Name": "Kyling"
  },
  {
    "First Name": "Carl",
    "Last Name": "LaBarba"
  },
  {
    "First Name": "Troy",
    "Last Name": "LaCrosse"
  },
  {
    "First Name": "Margot",
    "Last Name": "Ladd"
  },
  {
    "First Name": "Lockwood",
    "Last Name": "Lambeth"
  },
  {
    "First Name": "Reed",
    "Last Name": "Lange"
  },
  {
    "First Name": "Jeremy",
    "Last Name": "Langer"
  },
  {
    "First Name": "Parker",
    "Last Name": "Laredo"
  },
  {
    "First Name": "Elizabeth",
    "Last Name": "Laughlin"
  },
  {
    "First Name": "Jackson",
    "Last Name": "Laughry"
  },
  {
    "First Name": "Leif",
    "Last Name": "Lazenby"
  },
  {
    "First Name": "Kayla",
    "Last Name": "Le"
  },
  {
    "First Name": "Elizabeth",
    "Last Name": "Leary"
  },
  {
    "First Name": "Hugh",
    "Last Name": "Leblanc"
  },
  {
    "First Name": "Evelyn",
    "Last Name": "Leet"
  },
  {
    "First Name": "Caroline",
    "Last Name": "Liu"
  },
  {
    "First Name": "Samuel",
    "Last Name": "Llorente"
  },
  {
    "First Name": "Anzhelika",
    "Last Name": "Lobunko"
  },
  {
    "First Name": "Margaret",
    "Last Name": "Lockridge"
  },
  {
    "First Name": "Sophia",
    "Last Name": "Lomelo"
  },
  {
    "First Name": "Emery",
    "Last Name": "Lopez"
  },
  {
    "First Name": "Reagan",
    "Last Name": "Losey"
  },
  {
    "First Name": "Adelaide",
    "Last Name": "Lowes"
  },
  {
    "First Name": "Lilly",
    "Last Name": "Lucero"
  },
  {
    "First Name": "Sofia",
    "Last Name": "Ludvicek"
  },
  {
    "First Name": "Mary",
    "Last Name": "Lynch"
  },
  {
    "First Name": "Mead",
    "Last Name": "Lynch"
  },
  {
    "First Name": "Farrah",
    "Last Name": "Lyons"
  },
  {
    "First Name": "Lochlann",
    "Last Name": "Mackey"
  },
  {
    "First Name": "Merrick",
    "Last Name": "Magers"
  },
  {
    "First Name": "Amara",
    "Last Name": "Mahajan"
  },
  {
    "First Name": "Mark",
    "Last Name": "Mamminga"
  },
  {
    "First Name": "Philip",
    "Last Name": "Mandich"
  },
  {
    "First Name": "Garrett",
    "Last Name": "Marsh"
  },
  {
    "First Name": "Elizabeth",
    "Last Name": "Martin"
  },
  {
    "First Name": "Pierce",
    "Last Name": "Martin"
  },
  {
    "First Name": "Connelly",
    "Last Name": "Mason"
  },
  {
    "First Name": "Blake",
    "Last Name": "Matthews"
  },
  {
    "First Name": "Benjamin",
    "Last Name": "Mayfield"
  },
  {
    "First Name": "Richard",
    "Last Name": "McCallan"
  },
  {
    "First Name": "Loralei",
    "Last Name": "McCants"
  },
  {
    "First Name": "Michael",
    "Last Name": "McCarty"
  },
  {
    "First Name": "Hollins",
    "Last Name": "McCoy"
  },
  {
    "First Name": "Sophia",
    "Last Name": "McCoy"
  },
  {
    "First Name": "Tess",
    "Last Name": "McDonough"
  },
  {
    "First Name": "Alfred",
    "Last Name": "McEvoy"
  },
  {
    "First Name": "Lewis",
    "Last Name": "McMahan"
  },
  {
    "First Name": "Sebastian",
    "Last Name": "Meade"
  },
  {
    "First Name": "Thea",
    "Last Name": "Melech"
  },
  {
    "First Name": "Kyle",
    "Last Name": "Melson"
  },
  {
    "First Name": "Preston",
    "Last Name": "Melton"
  },
  {
    "First Name": "Brett",
    "Last Name": "Mentzer"
  },
  {
    "First Name": "Heidi",
    "Last Name": "Merritt"
  },
  {
    "First Name": "Wynne",
    "Last Name": "Meyer"
  },
  {
    "First Name": "Giselle",
    "Last Name": "Meyers"
  },
  {
    "First Name": "Mary Margaret",
    "Last Name": "Michelson"
  },
  {
    "First Name": "Ella",
    "Last Name": "Miller"
  },
  {
    "First Name": "Hogan",
    "Last Name": "Miller"
  },
  {
    "First Name": "Leo",
    "Last Name": "Minasoff"
  },
  {
    "First Name": "Carter",
    "Last Name": "Mitchell"
  },
  {
    "First Name": "Brayden",
    "Last Name": "Mitzel"
  },
  {
    "First Name": "Bentley",
    "Last Name": "Molnari"
  },
  {
    "First Name": "Mila",
    "Last Name": "Montes"
  },
  {
    "First Name": "Donovan",
    "Last Name": "Moore"
  },
  {
    "First Name": "Delara",
    "Last Name": "Moradi"
  },
  {
    "First Name": "Harper",
    "Last Name": "Morrow"
  },
  {
    "First Name": "Mack",
    "Last Name": "Morrow"
  },
  {
    "First Name": "Emerson",
    "Last Name": "Mossotti"
  },
  {
    "First Name": "Jaden",
    "Last Name": "Mudigere"
  },
  {
    "First Name": "Riley",
    "Last Name": "Mueller"
  },
  {
    "First Name": "Knox",
    "Last Name": "Mullen"
  },
  {
    "First Name": "Maxwell",
    "Last Name": "Mulroy"
  },
  {
    "First Name": "Julia",
    "Last Name": "Mundinger"
  },
  {
    "First Name": "Pearson",
    "Last Name": "Murff"
  },
  {
    "First Name": "Callie",
    "Last Name": "Musick"
  },
  {
    "First Name": "Dawson",
    "Last Name": "Neal"
  },
  {
    "First Name": "Lillian",
    "Last Name": "Neblett"
  },
  {
    "First Name": "Emory",
    "Last Name": "Neff"
  },
  {
    "First Name": "Catherine",
    "Last Name": "Nelson"
  },
  {
    "First Name": "Connor",
    "Last Name": "Newbold"
  },
  {
    "First Name": "Melissa",
    "Last Name": "Newman"
  },
  {
    "First Name": "Estelle",
    "Last Name": "Nguyen"
  },
  {
    "First Name": "Porter",
    "Last Name": "Nichols"
  },
  {
    "First Name": "Lauren",
    "Last Name": "Nierling"
  },
  {
    "First Name": "Reagan",
    "Last Name": "Nierling"
  },
  {
    "First Name": "John",
    "Last Name": "Nobles"
  },
  {
    "First Name": "Joseph",
    "Last Name": "Nobles"
  },
  {
    "First Name": "Lorraine",
    "Last Name": "Norvell"
  },
  {
    "First Name": "Nikko",
    "Last Name": "Numajiri"
  },
  {
    "First Name": "Sophie",
    "Last Name": "O'Connor"
  },
  {
    "First Name": "Cameron",
    "Last Name": "O'Neal"
  },
  {
    "First Name": "Liam",
    "Last Name": "Orchard"
  },
  {
    "First Name": "Elle",
    "Last Name": "Owens"
  },
  {
    "First Name": "Jacquelyn",
    "Last Name": "Ozsan"
  },
  {
    "First Name": "Violet",
    "Last Name": "Pagnam"
  },
  {
    "First Name": "Angela",
    "Last Name": "Pan"
  },
  {
    "First Name": "Shayan",
    "Last Name": "Pandey"
  },
  {
    "First Name": "Stefany",
    "Last Name": "Parra Ortiz"
  },
  {
    "First Name": "Adam",
    "Last Name": "Paterson"
  },
  {
    "First Name": "Campbell",
    "Last Name": "Patten"
  },
  {
    "First Name": "Millicent",
    "Last Name": "Patten"
  },
  {
    "First Name": "Thomas",
    "Last Name": "Payne"
  },
  {
    "First Name": "Amelia",
    "Last Name": "Peters"
  },
  {
    "First Name": "Daren",
    "Last Name": "Philip"
  },
  {
    "First Name": "Mabel",
    "Last Name": "Philips"
  },
  {
    "First Name": "Everly",
    "Last Name": "Phillips"
  },
  {
    "First Name": "Quinn",
    "Last Name": "Phillips"
  },
  {
    "First Name": "Wesley",
    "Last Name": "Phillips"
  },
  {
    "First Name": "James",
    "Last Name": "Porteous"
  },
  {
    "First Name": "Remington",
    "Last Name": "Presley"
  },
  {
    "First Name": "Ellie",
    "Last Name": "Price"
  },
  {
    "First Name": "Millicent",
    "Last Name": "Prieto"
  },
  {
    "First Name": "Molly",
    "Last Name": "Pyle"
  },
  {
    "First Name": "Connor",
    "Last Name": "Quigley"
  },
  {
    "First Name": "Harrison",
    "Last Name": "Radasky"
  },
  {
    "First Name": "Catherine",
    "Last Name": "Radford"
  },
  {
    "First Name": "Julia",
    "Last Name": "Raynor"
  },
  {
    "First Name": "Reid",
    "Last Name": "Reddick"
  },
  {
    "First Name": "Allison",
    "Last Name": "Reid"
  },
  {
    "First Name": "Samuel",
    "Last Name": "Rickords"
  },
  {
    "First Name": "Elijah",
    "Last Name": "Rivera"
  },
  {
    "First Name": "Charles",
    "Last Name": "Robertson"
  },
  {
    "First Name": "Colin",
    "Last Name": "Robertson"
  },
  {
    "First Name": "Ford",
    "Last Name": "Robertson"
  },
  {
    "First Name": "Henry",
    "Last Name": "Robertson"
  },
  {
    "First Name": "Luke",
    "Last Name": "Rockwood"
  },
  {
    "First Name": "Camila",
    "Last Name": "Rodriguez-Mora"
  },
  {
    "First Name": "Connor",
    "Last Name": "Roe"
  },
  {
    "First Name": "Reese",
    "Last Name": "Rowling"
  },
  {
    "First Name": "Reese",
    "Last Name": "Rugg"
  },
  {
    "First Name": "Roman",
    "Last Name": "Sales"
  },
  {
    "First Name": "Isabella",
    "Last Name": "Sanchez"
  },
  {
    "First Name": "Reese",
    "Last Name": "Sander"
  },
  {
    "First Name": "Dia",
    "Last Name": "Sandhu"
  },
  {
    "First Name": "Andrea",
    "Last Name": "Santos"
  },
  {
    "First Name": "Sloane",
    "Last Name": "Sarracino"
  },
  {
    "First Name": "Annie",
    "Last Name": "Schaufele"
  },
  {
    "First Name": "Matthew",
    "Last Name": "Schmidl"
  },
  {
    "First Name": "Anastyn",
    "Last Name": "Schroeder"
  },
  {
    "First Name": "Hayden",
    "Last Name": "Schultz"
  },
  {
    "First Name": "Margaret",
    "Last Name": "Schwarz"
  },
  {
    "First Name": "Clark",
    "Last Name": "Scott"
  },
  {
    "First Name": "Eleanor",
    "Last Name": "Seals"
  },
  {
    "First Name": "Ava",
    "Last Name": "Sears"
  },
  {
    "First Name": "Cameron",
    "Last Name": "Settle"
  },
  {
    "First Name": "Everleigh",
    "Last Name": "Shaikh"
  },
  {
    "First Name": "Mary",
    "Last Name": "Shoemaker"
  },
  {
    "First Name": "Alexandra",
    "Last Name": "Shultz"
  },
  {
    "First Name": "Avar",
    "Last Name": "Sidhu"
  },
  {
    "First Name": "Connor",
    "Last Name": "Singleton"
  },
  {
    "First Name": "Farren",
    "Last Name": "Slaughter"
  },
  {
    "First Name": "Bo",
    "Last Name": "Smith"
  },
  {
    "First Name": "Charlotte",
    "Last Name": "Smith"
  },
  {
    "First Name": "Joel",
    "Last Name": "Smith"
  },
  {
    "First Name": "Madeleine",
    "Last Name": "Smith"
  },
  {
    "First Name": "Graham",
    "Last Name": "Snoddy"
  },
  {
    "First Name": "John",
    "Last Name": "Somerville"
  },
  {
    "First Name": "Ellie",
    "Last Name": "Son"
  },
  {
    "First Name": "Sally",
    "Last Name": "Soper"
  },
  {
    "First Name": "Ty",
    "Last Name": "Starr"
  },
  {
    "First Name": "William",
    "Last Name": "Steddum"
  },
  {
    "First Name": "Dion",
    "Last Name": "Sun"
  },
  {
    "First Name": "Victoria",
    "Last Name": "Surdal"
  },
  {
    "First Name": "Anatoly",
    "Last Name": "Swafford"
  },
  {
    "First Name": "Robert",
    "Last Name": "Swope"
  },
  {
    "First Name": "Sally",
    "Last Name": "Swope"
  },
  {
    "First Name": "Sydney",
    "Last Name": "Taber"
  },
  {
    "First Name": "Aleksandar",
    "Last Name": "Tasic"
  },
  {
    "First Name": "Ellen",
    "Last Name": "Tate"
  },
  {
    "First Name": "Hudson",
    "Last Name": "Tatum"
  },
  {
    "First Name": "John",
    "Last Name": "Taylor"
  },
  {
    "First Name": "Haley",
    "Last Name": "Terry"
  },
  {
    "First Name": "Harper",
    "Last Name": "Terry"
  },
  {
    "First Name": "Parker",
    "Last Name": "Thompson"
  },
  {
    "First Name": "Ava",
    "Last Name": "Tomlin"
  },
  {
    "First Name": "Ella",
    "Last Name": "Tomlin"
  },
  {
    "First Name": "Davis",
    "Last Name": "Toups"
  },
  {
    "First Name": "James",
    "Last Name": "Toups"
  },
  {
    "First Name": "Greer",
    "Last Name": "Tremper"
  },
  {
    "First Name": "Milana",
    "Last Name": "Trivedi"
  },
  {
    "First Name": "Addison",
    "Last Name": "Trybus"
  },
  {
    "First Name": "Austin",
    "Last Name": "Trybus"
  },
  {
    "First Name": "Elias",
    "Last Name": "Tujios"
  },
  {
    "First Name": "Edison",
    "Last Name": "Turer"
  },
  {
    "First Name": "William",
    "Last Name": "Turner"
  },
  {
    "First Name": "Pablo",
    "Last Name": "Valle"
  },
  {
    "First Name": "Smith",
    "Last Name": "Varel"
  },
  {
    "First Name": "Vanna",
    "Last Name": "Vaughn"
  },
  {
    "First Name": "William",
    "Last Name": "Vergauwen"
  },
  {
    "First Name": "Logan",
    "Last Name": "Veski"
  },
  {
    "First Name": "Lincoln",
    "Last Name": "Wager"
  },
  {
    "First Name": "Sutton",
    "Last Name": "Walker"
  },
  {
    "First Name": "Vera",
    "Last Name": "Walker"
  },
  {
    "First Name": "John",
    "Last Name": "Wallace"
  },
  {
    "First Name": "Claire",
    "Last Name": "Walsh"
  },
  {
    "First Name": "Caleb",
    "Last Name": "Walters"
  },
  {
    "First Name": "Iris",
    "Last Name": "Wang"
  },
  {
    "First Name": "Samuel",
    "Last Name": "Wang"
  },
  {
    "First Name": "Edward",
    "Last Name": "Watts"
  },
  {
    "First Name": "Mary",
    "Last Name": "Wentworth"
  },
  {
    "First Name": "William",
    "Last Name": "Wheat"
  },
  {
    "First Name": "Claire",
    "Last Name": "Whitcomb"
  },
  {
    "First Name": "John",
    "Last Name": "White"
  },
  {
    "First Name": "Ava",
    "Last Name": "Wickard"
  },
  {
    "First Name": "Sophia",
    "Last Name": "Wilderman"
  },
  {
    "First Name": "Luke",
    "Last Name": "Wilkinson"
  },
  {
    "First Name": "Annabelle",
    "Last Name": "Williams"
  },
  {
    "First Name": "Brian",
    "Last Name": "Williams"
  },
  {
    "First Name": "James",
    "Last Name": "Williams"
  },
  {
    "First Name": "Finn",
    "Last Name": "Wittorf"
  },
  {
    "First Name": "Zoey",
    "Last Name": "Wong"
  },
  {
    "First Name": "Celine",
    "Last Name": "Xiao"
  },
  {
    "First Name": "Zachary",
    "Last Name": "Zaydler"
  },
  {
    "First Name": "Henry",
    "Last Name": "Ziebarth"
  },
  {
    "First Name": "Matthew",
    "Last Name": "Zurawel"
  },
  {
    "First Name": "Clark",
    "Last Name": "Abbott"
  },
  {
    "First Name": "Kylie",
    "Last Name": "Adam"
  },
  {
    "First Name": "Elizabeth",
    "Last Name": "Albergotti"
  },
  {
    "First Name": "Ford",
    "Last Name": "Alley"
  },
  {
    "First Name": "Abigail",
    "Last Name": "Allison"
  },
  {
    "First Name": "Athanasia",
    "Last Name": "Anderson"
  },
  {
    "First Name": "Charles",
    "Last Name": "Anderson"
  },
  {
    "First Name": "Emma-Grace",
    "Last Name": "Ariyo"
  },
  {
    "First Name": "Campbell",
    "Last Name": "Arviso"
  },
  {
    "First Name": "Caroline",
    "Last Name": "Ashby"
  },
  {
    "First Name": "Jordyn",
    "Last Name": "Ayoub"
  },
  {
    "First Name": "Liam",
    "Last Name": "Baghai"
  },
  {
    "First Name": "George",
    "Last Name": "Baker"
  },
  {
    "First Name": "Lucia",
    "Last Name": "Bank"
  },
  {
    "First Name": "Noelle",
    "Last Name": "Barfoot"
  },
  {
    "First Name": "Blakely",
    "Last Name": "Barragan"
  },
  {
    "First Name": "Hudson",
    "Last Name": "Bassett"
  },
  {
    "First Name": "Henry",
    "Last Name": "Beecherl"
  },
  {
    "First Name": "Margaret",
    "Last Name": "Bengtson"
  },
  {
    "First Name": "Brock",
    "Last Name": "Bennett"
  },
  {
    "First Name": "Olivia",
    "Last Name": "Berger"
  },
  {
    "First Name": "Luke",
    "Last Name": "Berlin"
  },
  {
    "First Name": "Leo",
    "Last Name": "Bigbee"
  },
  {
    "First Name": "Anna",
    "Last Name": "Bilbao"
  },
  {
    "First Name": "Emma",
    "Last Name": "Birdwell"
  },
  {
    "First Name": "Anna",
    "Last Name": "Bischoff"
  },
  {
    "First Name": "Grayson",
    "Last Name": "Blanchette"
  },
  {
    "First Name": "Andrew",
    "Last Name": "Bliss"
  },
  {
    "First Name": "Ella",
    "Last Name": "Bloede"
  },
  {
    "First Name": "Brynn",
    "Last Name": "Blurton"
  },
  {
    "First Name": "Sara",
    "Last Name": "Bocell"
  },
  {
    "First Name": "Alexander",
    "Last Name": "Bowman"
  },
  {
    "First Name": "William",
    "Last Name": "Boyd"
  },
  {
    "First Name": "Ella",
    "Last Name": "Bramhall"
  },
  {
    "First Name": "Tess",
    "Last Name": "Brooker"
  },
  {
    "First Name": "Barrett",
    "Last Name": "Brown"
  },
  {
    "First Name": "Bryce",
    "Last Name": "Brown"
  },
  {
    "First Name": "Anna",
    "Last Name": "Burdett"
  },
  {
    "First Name": "Beverly",
    "Last Name": "Butler"
  },
  {
    "First Name": "Michael",
    "Last Name": "Calce"
  },
  {
    "First Name": "Cole",
    "Last Name": "Cameron"
  },
  {
    "First Name": "Jay",
    "Last Name": "Cao"
  },
  {
    "First Name": "Chapel",
    "Last Name": "Carlson"
  },
  {
    "First Name": "Kelsey",
    "Last Name": "Carnahan"
  },
  {
    "First Name": "Cash",
    "Last Name": "Carpenter"
  },
  {
    "First Name": "Victoria",
    "Last Name": "Castellanos"
  },
  {
    "First Name": "Wolfe",
    "Last Name": "Cecere"
  },
  {
    "First Name": "Estella",
    "Last Name": "Chan"
  },
  {
    "First Name": "Lawson",
    "Last Name": "Chandler"
  },
  {
    "First Name": "Andrew",
    "Last Name": "Chapman"
  },
  {
    "First Name": "Olivia",
    "Last Name": "Chapman-Fox"
  },
  {
    "First Name": "Ava",
    "Last Name": "Cheatham"
  },
  {
    "First Name": "Naomi",
    "Last Name": "Chen"
  },
  {
    "First Name": "Andrew",
    "Last Name": "Chen"
  },
  {
    "First Name": "Stella",
    "Last Name": "Chen"
  },
  {
    "First Name": "Liam",
    "Last Name": "Chennault"
  },
  {
    "First Name": "Matthew",
    "Last Name": "Childs"
  },
  {
    "First Name": "Wyatt",
    "Last Name": "Chilian"
  },
  {
    "First Name": "Abigail",
    "Last Name": "Chong"
  },
  {
    "First Name": "Harper",
    "Last Name": "Christian"
  },
  {
    "First Name": "Ferguson",
    "Last Name": "Clark"
  },
  {
    "First Name": "Rosalyn",
    "Last Name": "Colangelo"
  },
  {
    "First Name": "Alp",
    "Last Name": "Colasan"
  },
  {
    "First Name": "Savannah",
    "Last Name": "Colenso"
  },
  {
    "First Name": "Saxon",
    "Last Name": "Compton"
  },
  {
    "First Name": "Mary",
    "Last Name": "Conger"
  },
  {
    "First Name": "Leila",
    "Last Name": "Conlan"
  },
  {
    "First Name": "Sydney",
    "Last Name": "Conley"
  },
  {
    "First Name": "Holland",
    "Last Name": "Cook"
  },
  {
    "First Name": "Jackson",
    "Last Name": "Cooksey"
  },
  {
    "First Name": "Douglas",
    "Last Name": "Cooper"
  },
  {
    "First Name": "Charles",
    "Last Name": "Corder"
  },
  {
    "First Name": "Neely",
    "Last Name": "Cordon"
  },
  {
    "First Name": "Andrea",
    "Last Name": "Cosme"
  },
  {
    "First Name": "Bradley",
    "Last Name": "Coussens"
  },
  {
    "First Name": "Austin",
    "Last Name": "Crain"
  },
  {
    "First Name": "Edward",
    "Last Name": "Crawford"
  },
  {
    "First Name": "Henry",
    "Last Name": "Cree"
  },
  {
    "First Name": "Harold",
    "Last Name": "Crisinel"
  },
  {
    "First Name": "Claire",
    "Last Name": "Crosby"
  },
  {
    "First Name": "Walker",
    "Last Name": "Crosland"
  },
  {
    "First Name": "Lane",
    "Last Name": "Crow"
  },
  {
    "First Name": "Christopher",
    "Last Name": "Crump"
  },
  {
    "First Name": "Nicholas",
    "Last Name": "Crump"
  },
  {
    "First Name": "Holly",
    "Last Name": "Cullum"
  },
  {
    "First Name": "Elaa",
    "Last Name": "Dahan"
  },
  {
    "First Name": "Katherine",
    "Last Name": "Dalrymple"
  },
  {
    "First Name": "Poppy",
    "Last Name": "DaSilva"
  },
  {
    "First Name": "Madeline",
    "Last Name": "Davenport"
  },
  {
    "First Name": "Virginia",
    "Last Name": "Dering"
  },
  {
    "First Name": "Darian",
    "Last Name": "Dezham"
  },
  {
    "First Name": "Eloise",
    "Last Name": "Diaz Mathe"
  },
  {
    "First Name": "Claire",
    "Last Name": "Draper"
  },
  {
    "First Name": "Dax",
    "Last Name": "Drennan"
  },
  {
    "First Name": "Caitlin",
    "Last Name": "Duff"
  },
  {
    "First Name": "Berkley",
    "Last Name": "Durham"
  },
  {
    "First Name": "Ari",
    "Last Name": "Durham"
  },
  {
    "First Name": "Leigh",
    "Last Name": "Dyer"
  },
  {
    "First Name": "Mary",
    "Last Name": "Dyer"
  },
  {
    "First Name": "Farah",
    "Last Name": "Edmondson"
  },
  {
    "First Name": "William",
    "Last Name": "Ellis"
  },
  {
    "First Name": "James",
    "Last Name": "Elmore"
  },
  {
    "First Name": "Emma",
    "Last Name": "Elverum"
  },
  {
    "First Name": "Abby",
    "Last Name": "Engstrom"
  },
  {
    "First Name": "Hayden",
    "Last Name": "Ernst"
  },
  {
    "First Name": "James",
    "Last Name": "Evans"
  },
  {
    "First Name": "Macy",
    "Last Name": "Evenson"
  },
  {
    "First Name": "Maya",
    "Last Name": "Evenson"
  },
  {
    "First Name": "Marye",
    "Last Name": "Evenson"
  },
  {
    "First Name": "Lillian",
    "Last Name": "Fabris"
  },
  {
    "First Name": "Kyran",
    "Last Name": "Faires"
  },
  {
    "First Name": "Liam",
    "Last Name": "Fan"
  },
  {
    "First Name": "Adrian",
    "Last Name": "Farahani"
  },
  {
    "First Name": "Conrad",
    "Last Name": "Ferguson"
  },
  {
    "First Name": "Grace",
    "Last Name": "Ferguson"
  },
  {
    "First Name": "Virginia",
    "Last Name": "Ferrell"
  },
  {
    "First Name": "Bendy",
    "Last Name": "Filgo"
  },
  {
    "First Name": "Paul",
    "Last Name": "Fletcher"
  },
  {
    "First Name": "Nolan",
    "Last Name": "Fletcher"
  },
  {
    "First Name": "Andrew",
    "Last Name": "Flowers"
  },
  {
    "First Name": "Tristan",
    "Last Name": "Fogarty-Williamson"
  },
  {
    "First Name": "Hallie",
    "Last Name": "Fuller"
  },
  {
    "First Name": "William",
    "Last Name": "Fuqua"
  },
  {
    "First Name": "Arden",
    "Last Name": "Gaither"
  },
  {
    "First Name": "Thaxton",
    "Last Name": "Gallo"
  },
  {
    "First Name": "Pedro",
    "Last Name": "Garcia Villalon"
  },
  {
    "First Name": "Olivia",
    "Last Name": "Gasch"
  },
  {
    "First Name": "Zachary",
    "Last Name": "Gerhardt"
  },
  {
    "First Name": "Taylor",
    "Last Name": "Gibson"
  },
  {
    "First Name": "Granger",
    "Last Name": "Gillespie"
  },
  {
    "First Name": "Chloe",
    "Last Name": "Gillette"
  },
  {
    "First Name": "Kate",
    "Last Name": "Gilmore"
  },
  {
    "First Name": "Isabella",
    "Last Name": "Glover"
  },
  {
    "First Name": "Eleanor",
    "Last Name": "Goldman"
  },
  {
    "First Name": "Chloe",
    "Last Name": "Gordon"
  },
  {
    "First Name": "Piper",
    "Last Name": "Gray"
  },
  {
    "First Name": "Parker",
    "Last Name": "Green"
  },
  {
    "First Name": "Sloane",
    "Last Name": "Green"
  },
  {
    "First Name": "Margaret",
    "Last Name": "Grider"
  },
  {
    "First Name": "Shepperd",
    "Last Name": "Griffin"
  },
  {
    "First Name": "Seth",
    "Last Name": "Hamilton"
  },
  {
    "First Name": "Hadley",
    "Last Name": "Hammel"
  },
  {
    "First Name": "Benjamin",
    "Last Name": "Hardaway"
  },
  {
    "First Name": "Morgan",
    "Last Name": "Harris"
  },
  {
    "First Name": "Archer",
    "Last Name": "Harris"
  },
  {
    "First Name": "Luke",
    "Last Name": "Hart"
  },
  {
    "First Name": "Katherine",
    "Last Name": "Harvey"
  },
  {
    "First Name": "Olivia",
    "Last Name": "Harvey"
  },
  {
    "First Name": "Dylan",
    "Last Name": "Hayashi"
  },
  {
    "First Name": "Andrew",
    "Last Name": "Head"
  },
  {
    "First Name": "Caitlyn",
    "Last Name": "Heckler"
  },
  {
    "First Name": "Wyatt",
    "Last Name": "Heffelfinger"
  },
  {
    "First Name": "Campbell",
    "Last Name": "Hefner"
  },
  {
    "First Name": "Caroline",
    "Last Name": "Hefty"
  },
  {
    "First Name": "Hunter",
    "Last Name": "Heiss"
  },
  {
    "First Name": "Henry",
    "Last Name": "Helm"
  },
  {
    "First Name": "Lottie",
    "Last Name": "Henderson"
  },
  {
    "First Name": "Hudson",
    "Last Name": "Henning"
  },
  {
    "First Name": "Davis",
    "Last Name": "Henry"
  },
  {
    "First Name": "Luke",
    "Last Name": "Herron"
  },
  {
    "First Name": "Elise",
    "Last Name": "Hightower"
  },
  {
    "First Name": "Avery-Harper",
    "Last Name": "Hill"
  },
  {
    "First Name": "Hunter",
    "Last Name": "Hill"
  },
  {
    "First Name": "Alexis",
    "Last Name": "Hoaglund"
  },
  {
    "First Name": "Ashley",
    "Last Name": "Hoaglund"
  },
  {
    "First Name": "Isabella",
    "Last Name": "Hoang"
  },
  {
    "First Name": "Alice",
    "Last Name": "Hodges"
  },
  {
    "First Name": "Wilson",
    "Last Name": "Hornbach"
  },
  {
    "First Name": "Khloe",
    "Last Name": "Horstman"
  },
  {
    "First Name": "Mary",
    "Last Name": "Hrncir"
  },
  {
    "First Name": "Yuchen",
    "Last Name": "Hua"
  },
  {
    "First Name": "Anna",
    "Last Name": "Hubbard"
  },
  {
    "First Name": "Hawkins",
    "Last Name": "Huffstutter"
  },
  {
    "First Name": "James",
    "Last Name": "Hunt"
  },
  {
    "First Name": "Thomas",
    "Last Name": "Hunt"
  },
  {
    "First Name": "Miyoko",
    "Last Name": "Hunter"
  },
  {
    "First Name": "London",
    "Last Name": "Iliff"
  },
  {
    "First Name": "Wesley",
    "Last Name": "Jackson"
  },
  {
    "First Name": "Devin",
    "Last Name": "Jackson"
  },
  {
    "First Name": "William",
    "Last Name": "Jackson"
  },
  {
    "First Name": "Emerson",
    "Last Name": "Jacobs"
  },
  {
    "First Name": "Jesse",
    "Last Name": "James"
  },
  {
    "First Name": "Jack",
    "Last Name": "Jaudes"
  },
  {
    "First Name": "Alexandra",
    "Last Name": "Jee"
  },
  {
    "First Name": "Maximilian",
    "Last Name": "Jee"
  },
  {
    "First Name": "Augustus",
    "Last Name": "Jennings"
  },
  {
    "First Name": "Grafton",
    "Last Name": "Jodry"
  },
  {
    "First Name": "Blake",
    "Last Name": "Johnson"
  },
  {
    "First Name": "Knox",
    "Last Name": "Johnson"
  },
  {
    "First Name": "Leah",
    "Last Name": "Johnson"
  },
  {
    "First Name": "Luke",
    "Last Name": "Johnson"
  },
  {
    "First Name": "Calvin",
    "Last Name": "Johnston"
  },
  {
    "First Name": "Hadassah",
    "Last Name": "Karr"
  },
  {
    "First Name": "Anderson",
    "Last Name": "Katz"
  },
  {
    "First Name": "Rowan",
    "Last Name": "Keenan"
  },
  {
    "First Name": "Anna",
    "Last Name": "Keene"
  },
  {
    "First Name": "Emily",
    "Last Name": "Kerr"
  },
  {
    "First Name": "Eva",
    "Last Name": "Kim"
  },
  {
    "First Name": "Caroline",
    "Last Name": "Kipp"
  },
  {
    "First Name": "Martin",
    "Last Name": "Klein"
  },
  {
    "First Name": "Lynn",
    "Last Name": "Kobayashi"
  },
  {
    "First Name": "Daniel",
    "Last Name": "Koro"
  },
  {
    "First Name": "Samir",
    "Last Name": "Koro"
  },
  {
    "First Name": "Leonidas",
    "Last Name": "Kottos"
  },
  {
    "First Name": "Bumjun",
    "Last Name": "Kwon"
  },
  {
    "First Name": "Roman",
    "Last Name": "LaCrosse"
  },
  {
    "First Name": "Leah",
    "Last Name": "Laczkowski"
  },
  {
    "First Name": "John",
    "Last Name": "LaGere"
  },
  {
    "First Name": "Stella",
    "Last Name": "Lang"
  },
  {
    "First Name": "Griffin",
    "Last Name": "Lazebnik"
  },
  {
    "First Name": "Mila",
    "Last Name": "Le"
  },
  {
    "First Name": "Chloe",
    "Last Name": "Lee"
  },
  {
    "First Name": "William",
    "Last Name": "Leidner"
  },
  {
    "First Name": "William",
    "Last Name": "Lester"
  },
  {
    "First Name": "Bennett",
    "Last Name": "Lewis"
  },
  {
    "First Name": "Brynn",
    "Last Name": "Lewis"
  },
  {
    "First Name": "Olivia",
    "Last Name": "Liu"
  },
  {
    "First Name": "Matthew",
    "Last Name": "Longo"
  },
  {
    "First Name": "Hanson",
    "Last Name": "Lou"
  },
  {
    "First Name": "Liam",
    "Last Name": "Lucero"
  },
  {
    "First Name": "Alina",
    "Last Name": "Manhas"
  },
  {
    "First Name": "Anna",
    "Last Name": "Markin"
  },
  {
    "First Name": "Benjamin",
    "Last Name": "Marshall"
  },
  {
    "First Name": "Nathan",
    "Last Name": "Marx"
  },
  {
    "First Name": "Abigail",
    "Last Name": "Mathew"
  },
  {
    "First Name": "Exa",
    "Last Name": "McCathern"
  },
  {
    "First Name": "Lila",
    "Last Name": "McCollum"
  },
  {
    "First Name": "Hunter",
    "Last Name": "McCombs"
  },
  {
    "First Name": "Henry",
    "Last Name": "McCracken"
  },
  {
    "First Name": "Olivia",
    "Last Name": "McEnturff"
  },
  {
    "First Name": "Harper",
    "Last Name": "McGuire"
  },
  {
    "First Name": "Madeleine",
    "Last Name": "Meghrabi"
  },
  {
    "First Name": "Hadleigh",
    "Last Name": "Merkle"
  },
  {
    "First Name": "Gemma",
    "Last Name": "Merrick"
  },
  {
    "First Name": "Jackson",
    "Last Name": "Merwin"
  },
  {
    "First Name": "Katharynne",
    "Last Name": "Metcalf"
  },
  {
    "First Name": "Asher",
    "Last Name": "Meyer"
  },
  {
    "First Name": "Joy",
    "Last Name": "Miller"
  },
  {
    "First Name": "June",
    "Last Name": "Miller"
  },
  {
    "First Name": "Thomas",
    "Last Name": "Miller"
  },
  {
    "First Name": "Avery",
    "Last Name": "Miller"
  },
  {
    "First Name": "Gwyneth",
    "Last Name": "Miller"
  },
  {
    "First Name": "Natalie",
    "Last Name": "Miller"
  },
  {
    "First Name": "Juliette",
    "Last Name": "Mitchell"
  },
  {
    "First Name": "Julian",
    "Last Name": "Moon"
  },
  {
    "First Name": "Lawson",
    "Last Name": "Moore"
  },
  {
    "First Name": "Brody",
    "Last Name": "Moreno"
  },
  {
    "First Name": "Maxwell",
    "Last Name": "Moreno"
  },
  {
    "First Name": "McCoy",
    "Last Name": "Moss"
  },
  {
    "First Name": "Kevin",
    "Last Name": "Mostafaie"
  },
  {
    "First Name": "Lincoln",
    "Last Name": "Mueller"
  },
  {
    "First Name": "Amelie",
    "Last Name": "Muller"
  },
  {
    "First Name": "Kate",
    "Last Name": "Mullikin"
  },
  {
    "First Name": "Lauren",
    "Last Name": "Mullikin"
  },
  {
    "First Name": "Catherine",
    "Last Name": "Musselman"
  },
  {
    "First Name": "John",
    "Last Name": "Neff"
  },
  {
    "First Name": "Andrew",
    "Last Name": "Nelson"
  },
  {
    "First Name": "Claire",
    "Last Name": "Nunley"
  },
  {
    "First Name": "Bennett",
    "Last Name": "Nutter"
  },
  {
    "First Name": "Ava",
    "Last Name": "O'Banion"
  },
  {
    "First Name": "Charlotte",
    "Last Name": "OBoyle"
  },
  {
    "First Name": "George",
    "Last Name": "O'Grady"
  },
  {
    "First Name": "Elinor",
    "Last Name": "OLVERA IRIGOYEN"
  },
  {
    "First Name": "Auden",
    "Last Name": "Ortiz"
  },
  {
    "First Name": "Anne",
    "Last Name": "Owen"
  },
  {
    "First Name": "Mira",
    "Last Name": "Ozbilek"
  },
  {
    "First Name": "Britton",
    "Last Name": "Pace"
  },
  {
    "First Name": "Bea",
    "Last Name": "Pacholski"
  },
  {
    "First Name": "Sarah",
    "Last Name": "Palmer"
  },
  {
    "First Name": "Lorelei",
    "Last Name": "Parma"
  },
  {
    "First Name": "Nikki",
    "Last Name": "Parvizi"
  },
  {
    "First Name": "Samuel",
    "Last Name": "Pate"
  },
  {
    "First Name": "Hadley",
    "Last Name": "Paul"
  },
  {
    "First Name": "Eisley",
    "Last Name": "Paulsen"
  },
  {
    "First Name": "Arthur",
    "Last Name": "Peck"
  },
  {
    "First Name": "Nathan",
    "Last Name": "Pekar"
  },
  {
    "First Name": "Audrey",
    "Last Name": "Pennington"
  },
  {
    "First Name": "Oghie",
    "Last Name": "Peters"
  },
  {
    "First Name": "Sydney",
    "Last Name": "Peterson"
  },
  {
    "First Name": "Libby",
    "Last Name": "Petet"
  },
  {
    "First Name": "Elizabeth",
    "Last Name": "Petit"
  },
  {
    "First Name": "Eva",
    "Last Name": "Petrone"
  },
  {
    "First Name": "Landon",
    "Last Name": "Pham"
  },
  {
    "First Name": "Emerson",
    "Last Name": "Pielsticker"
  },
  {
    "First Name": "Sullivan",
    "Last Name": "Pierre"
  },
  {
    "First Name": "Wynne",
    "Last Name": "Piland"
  },
  {
    "First Name": "Evelyn",
    "Last Name": "Pillers"
  },
  {
    "First Name": "Robert",
    "Last Name": "Pincoffs"
  },
  {
    "First Name": "Macrina",
    "Last Name": "Popa"
  },
  {
    "First Name": "Wells",
    "Last Name": "Pope"
  },
  {
    "First Name": "Carson",
    "Last Name": "Powers"
  },
  {
    "First Name": "Holt",
    "Last Name": "Preston"
  },
  {
    "First Name": "Audrey",
    "Last Name": "Price"
  },
  {
    "First Name": "Anna",
    "Last Name": "Primavera"
  },
  {
    "First Name": "Andrew",
    "Last Name": "Primavera"
  },
  {
    "First Name": "Milam",
    "Last Name": "Pullen"
  },
  {
    "First Name": "Elisabeth",
    "Last Name": "Pulliam"
  },
  {
    "First Name": "Alvin",
    "Last Name": "Qin"
  },
  {
    "First Name": "Ziquan",
    "Last Name": "Qiu"
  },
  {
    "First Name": "Joaquin",
    "Last Name": "Ramirez"
  },
  {
    "First Name": "Bradley",
    "Last Name": "Ramo"
  },
  {
    "First Name": "Ethan",
    "Last Name": "Ramo"
  },
  {
    "First Name": "Nicole",
    "Last Name": "Reed"
  },
  {
    "First Name": "Georgia",
    "Last Name": "Reed"
  },
  {
    "First Name": "William",
    "Last Name": "Reed"
  },
  {
    "First Name": "Willow",
    "Last Name": "Renna"
  },
  {
    "First Name": "Sofia",
    "Last Name": "Reyer"
  },
  {
    "First Name": "Eli",
    "Last Name": "Reynolds"
  },
  {
    "First Name": "Molly",
    "Last Name": "Roach"
  },
  {
    "First Name": "Rylan",
    "Last Name": "Robbins"
  },
  {
    "First Name": "Lily",
    "Last Name": "Roberson"
  },
  {
    "First Name": "Hudson",
    "Last Name": "Roby"
  },
  {
    "First Name": "Violet",
    "Last Name": "Rockow"
  },
  {
    "First Name": "Thomas",
    "Last Name": "Roglan"
  },
  {
    "First Name": "Alec",
    "Last Name": "Rojas"
  },
  {
    "First Name": "Gray",
    "Last Name": "Rosen"
  },
  {
    "First Name": "William",
    "Last Name": "Roslund"
  },
  {
    "First Name": "Anna",
    "Last Name": "Roth"
  },
  {
    "First Name": "Jack",
    "Last Name": "Rugg"
  },
  {
    "First Name": "Rex",
    "Last Name": "Ruth"
  },
  {
    "First Name": "Benton",
    "Last Name": "Rutledge"
  },
  {
    "First Name": "Antonina",
    "Last Name": "Sachse"
  },
  {
    "First Name": "William",
    "Last Name": "Santa Maria"
  },
  {
    "First Name": "Marcela",
    "Last Name": "Santos"
  },
  {
    "First Name": "Henry",
    "Last Name": "Sauder"
  },
  {
    "First Name": "Dean",
    "Last Name": "Savage"
  },
  {
    "First Name": "Wesley",
    "Last Name": "Scarff"
  },
  {
    "First Name": "Sally",
    "Last Name": "Schaufele"
  },
  {
    "First Name": "Andrew",
    "Last Name": "Schmidl"
  },
  {
    "First Name": "Jason",
    "Last Name": "Schmidt"
  },
  {
    "First Name": "Aida",
    "Last Name": "Schnyder"
  },
  {
    "First Name": "Eva",
    "Last Name": "Schopp"
  },
  {
    "First Name": "Henry",
    "Last Name": "Schultis"
  },
  {
    "First Name": "Miles",
    "Last Name": "Schuttler"
  },
  {
    "First Name": "Juliana",
    "Last Name": "Scully"
  },
  {
    "First Name": "Phelps",
    "Last Name": "Sears"
  },
  {
    "First Name": "Drew",
    "Last Name": "Sherman"
  },
  {
    "First Name": "Lily",
    "Last Name": "Shi"
  },
  {
    "First Name": "Julianna",
    "Last Name": "Shoemaker"
  },
  {
    "First Name": "Clifton",
    "Last Name": "Shore"
  },
  {
    "First Name": "William",
    "Last Name": "Short"
  },
  {
    "First Name": "Alexa",
    "Last Name": "Shufeldt"
  },
  {
    "First Name": "Lucian",
    "Last Name": "Siegwart"
  },
  {
    "First Name": "Jette",
    "Last Name": "Simmons"
  },
  {
    "First Name": "Charles",
    "Last Name": "Simons"
  },
  {
    "First Name": "Samuel",
    "Last Name": "Simons"
  },
  {
    "First Name": "Aalamjeet",
    "Last Name": "Singh"
  },
  {
    "First Name": "Neely",
    "Last Name": "Singleton"
  },
  {
    "First Name": "Charlotte",
    "Last Name": "Slade"
  },
  {
    "First Name": "Charles",
    "Last Name": "Small"
  },
  {
    "First Name": "Carson",
    "Last Name": "Smetko"
  },
  {
    "First Name": "Siena",
    "Last Name": "Smith"
  },
  {
    "First Name": "Laney",
    "Last Name": "Sontag"
  },
  {
    "First Name": "Blake",
    "Last Name": "Speer"
  },
  {
    "First Name": "Sadie",
    "Last Name": "Stabler"
  },
  {
    "First Name": "Olivia",
    "Last Name": "Stanwood"
  },
  {
    "First Name": "Vander",
    "Last Name": "Stapp"
  },
  {
    "First Name": "Stella",
    "Last Name": "Steffen"
  },
  {
    "First Name": "Layla",
    "Last Name": "Steward"
  },
  {
    "First Name": "Rhett",
    "Last Name": "Stienke"
  },
  {
    "First Name": "Clayton",
    "Last Name": "Stroup"
  },
  {
    "First Name": "Sabrina",
    "Last Name": "Summerall"
  },
  {
    "First Name": "Chloe",
    "Last Name": "Sun"
  },
  {
    "First Name": "Josie",
    "Last Name": "Sun"
  },
  {
    "First Name": "Michael",
    "Last Name": "Swaldi"
  },
  {
    "First Name": "Holt",
    "Last Name": "Swanson"
  },
  {
    "First Name": "Thomas",
    "Last Name": "Sylvan"
  },
  {
    "First Name": "Samia",
    "Last Name": "Taher"
  },
  {
    "First Name": "Preston",
    "Last Name": "Talley"
  },
  {
    "First Name": "James",
    "Last Name": "Talley"
  },
  {
    "First Name": "Ansley",
    "Last Name": "Taub"
  },
  {
    "First Name": "Summit",
    "Last Name": "Tauscher"
  },
  {
    "First Name": "Philip",
    "Last Name": "Taylor"
  },
  {
    "First Name": "Avery",
    "Last Name": "Terry"
  },
  {
    "First Name": "Victoria",
    "Last Name": "Thanos"
  },
  {
    "First Name": "Brady",
    "Last Name": "Thibodeau"
  },
  {
    "First Name": "Ellery",
    "Last Name": "Thomas"
  },
  {
    "First Name": "Lillian",
    "Last Name": "Thomas"
  },
  {
    "First Name": "Molly",
    "Last Name": "Thornfield"
  },
  {
    "First Name": "Olivia",
    "Last Name": "Toce"
  },
  {
    "First Name": "Matthew",
    "Last Name": "Torgan"
  },
  {
    "First Name": "Khanh",
    "Last Name": "Tran"
  },
  {
    "First Name": "Ty",
    "Last Name": "Tremper"
  },
  {
    "First Name": "William",
    "Last Name": "Tuohy"
  },
  {
    "First Name": "Claire",
    "Last Name": "Turnbull"
  },
  {
    "First Name": "Mary",
    "Last Name": "Ulrich"
  },
  {
    "First Name": "William",
    "Last Name": "Vahrenkamp"
  },
  {
    "First Name": "Harper",
    "Last Name": "Van Dorn"
  },
  {
    "First Name": "CAMILA",
    "Last Name": "VANDERVINNE"
  },
  {
    "First Name": "Jack",
    "Last Name": "Vardeman"
  },
  {
    "First Name": "Natalia",
    "Last Name": "Vasquez"
  },
  {
    "First Name": "Tara",
    "Last Name": "Vaughn"
  },
  {
    "First Name": "Hudson",
    "Last Name": "Ventouras"
  },
  {
    "First Name": "Charles",
    "Last Name": "Vergauwen"
  },
  {
    "First Name": "Kostadena",
    "Last Name": "Vergos"
  },
  {
    "First Name": "Zoe",
    "Last Name": "Vergos"
  },
  {
    "First Name": "Santiago",
    "Last Name": "Villalba Garduno"
  },
  {
    "First Name": "Victoria",
    "Last Name": "Vineyard"
  },
  {
    "First Name": "Landen",
    "Last Name": "Wager"
  },
  {
    "First Name": "Kathleen",
    "Last Name": "Waldron"
  },
  {
    "First Name": "Margaux",
    "Last Name": "Wallace"
  },
  {
    "First Name": "Joseph",
    "Last Name": "Wang"
  },
  {
    "First Name": "Raquel",
    "Last Name": "Ward"
  },
  {
    "First Name": "Jack",
    "Last Name": "Webb"
  },
  {
    "First Name": "Brooks",
    "Last Name": "Wells"
  },
  {
    "First Name": "Miller",
    "Last Name": "West"
  },
  {
    "First Name": "Hobbs",
    "Last Name": "Whatley"
  },
  {
    "First Name": "Mary",
    "Last Name": "Wick"
  },
  {
    "First Name": "Braden",
    "Last Name": "Widmer"
  },
  {
    "First Name": "Apple",
    "Last Name": "Wiegand"
  },
  {
    "First Name": "William",
    "Last Name": "Wilkie"
  },
  {
    "First Name": "Alexandra",
    "Last Name": "Williams"
  },
  {
    "First Name": "William",
    "Last Name": "Wilson"
  },
  {
    "First Name": "Evan",
    "Last Name": "Witt"
  },
  {
    "First Name": "Grace",
    "Last Name": "Woldert"
  },
  {
    "First Name": "Lila",
    "Last Name": "Wortman"
  },
  {
    "First Name": "Jetty",
    "Last Name": "Wright"
  },
  {
    "First Name": "Tessa",
    "Last Name": "Wu"
  },
  {
    "First Name": "Jackson",
    "Last Name": "Xu"
  },
  {
    "First Name": "Hannah",
    "Last Name": "Yi"
  },
  {
    "First Name": "Eli",
    "Last Name": "Yonker"
  },
  {
    "First Name": "Caleb",
    "Last Name": "Yoon"
  },
  {
    "First Name": "Grant",
    "Last Name": "Young"
  },
  {
    "First Name": "Willa",
    "Last Name": "Zakrocki"
  },
  {
    "First Name": "Mark",
    "Last Name": "Zantop"
  },
  {
    "First Name": "Benjamin",
    "Last Name": "Zapffe"
  },
  {
    "First Name": "Lucy",
    "Last Name": "Zaptin"
  },
  {
    "First Name": "Lilly",
    "Last Name": "Zeitman"
  },
  {
    "First Name": "Julia",
    "Last Name": "Zhang"
  },
  {
    "First Name": "Mingbo",
    "Last Name": "Zhang"
  },
  {
    "First Name": "Abdul-Malik",
    "Last Name": "Abubakar"
  },
  {
    "First Name": "Milo",
    "Last Name": "Adames"
  },
  {
    "First Name": "Liam",
    "Last Name": "Adami"
  },
  {
    "First Name": "Lila",
    "Last Name": "Adams"
  },
  {
    "First Name": "Laila",
    "Last Name": "Alfia"
  },
  {
    "First Name": "Charles",
    "Last Name": "Allen"
  },
  {
    "First Name": "Hall",
    "Last Name": "Allison"
  },
  {
    "First Name": "Genesis",
    "Last Name": "Alphonsus Ekwerike"
  },
  {
    "First Name": "Madison",
    "Last Name": "Amos"
  },
  {
    "First Name": "Knox",
    "Last Name": "Andersen"
  },
  {
    "First Name": "Ava",
    "Last Name": "Anderson"
  },
  {
    "First Name": "Heidi",
    "Last Name": "Anderson"
  },
  {
    "First Name": "Thomas",
    "Last Name": "Anding"
  },
  {
    "First Name": "Stone",
    "Last Name": "Andrews"
  },
  {
    "First Name": "Christopher",
    "Last Name": "Applewhite"
  },
  {
    "First Name": "Holland",
    "Last Name": "Armstrong"
  },
  {
    "First Name": "Emma",
    "Last Name": "August"
  },
  {
    "First Name": "Zoe",
    "Last Name": "Avalos"
  },
  {
    "First Name": "Camden",
    "Last Name": "Ayoub"
  },
  {
    "First Name": "Paxton",
    "Last Name": "Ayoub"
  },
  {
    "First Name": "Alexa",
    "Last Name": "Baker"
  },
  {
    "First Name": "Ella",
    "Last Name": "Balding"
  },
  {
    "First Name": "Hailey",
    "Last Name": "Baldwin"
  },
  {
    "First Name": "James",
    "Last Name": "Balfour"
  },
  {
    "First Name": "Grace",
    "Last Name": "Ballard"
  },
  {
    "First Name": "Milan",
    "Last Name": "Banks"
  },
  {
    "First Name": "Jack",
    "Last Name": "Barker"
  },
  {
    "First Name": "Caroline",
    "Last Name": "Baskin"
  },
  {
    "First Name": "Madison",
    "Last Name": "Baskin"
  },
  {
    "First Name": "Marcus",
    "Last Name": "Bavry"
  },
  {
    "First Name": "Betsy",
    "Last Name": "Beakley"
  },
  {
    "First Name": "Reese",
    "Last Name": "Beck"
  },
  {
    "First Name": "Michael",
    "Last Name": "Beecherl"
  },
  {
    "First Name": "James",
    "Last Name": "Begert"
  },
  {
    "First Name": "Elise",
    "Last Name": "Bennett"
  },
  {
    "First Name": "Paul",
    "Last Name": "Bennett"
  },
  {
    "First Name": "Barrett",
    "Last Name": "Benson"
  },
  {
    "First Name": "Graeme",
    "Last Name": "Berry"
  },
  {
    "First Name": "Alara",
    "Last Name": "Bigbee"
  },
  {
    "First Name": "Ben",
    "Last Name": "Biggers"
  },
  {
    "First Name": "Mary",
    "Last Name": "Bill"
  },
  {
    "First Name": "Julia",
    "Last Name": "Blades"
  },
  {
    "First Name": "Andrew",
    "Last Name": "Blanchard"
  },
  {
    "First Name": "Ava",
    "Last Name": "Bock"
  },
  {
    "First Name": "Michael",
    "Last Name": "Bonfield"
  },
  {
    "First Name": "Maggie",
    "Last Name": "Boone"
  },
  {
    "First Name": "Jackson",
    "Last Name": "Boucher"
  },
  {
    "First Name": "Kaitlyn",
    "Last Name": "Bourgeois"
  },
  {
    "First Name": "BRYN",
    "Last Name": "BOWEN"
  },
  {
    "First Name": "Margarette",
    "Last Name": "Bowles"
  },
  {
    "First Name": "Olivia",
    "Last Name": "Brack"
  },
  {
    "First Name": "Charles",
    "Last Name": "Bradbury"
  },
  {
    "First Name": "Bailey",
    "Last Name": "Braidfoot"
  },
  {
    "First Name": "Mae",
    "Last Name": "Bridges"
  },
  {
    "First Name": "Taylor",
    "Last Name": "Bristow"
  },
  {
    "First Name": "Madelyn",
    "Last Name": "Brown"
  },
  {
    "First Name": "Andrew",
    "Last Name": "Brown"
  },
  {
    "First Name": "Ava",
    "Last Name": "Brown"
  },
  {
    "First Name": "Brendan",
    "Last Name": "Brown"
  },
  {
    "First Name": "Briley",
    "Last Name": "Brown"
  },
  {
    "First Name": "Cord",
    "Last Name": "Brown"
  },
  {
    "First Name": "Bishan",
    "Last Name": "Butani"
  },
  {
    "First Name": "Linsey",
    "Last Name": "Cai"
  },
  {
    "First Name": "Trey",
    "Last Name": "Cantrell"
  },
  {
    "First Name": "Henrique",
    "Last Name": "Cardoso Melo"
  },
  {
    "First Name": "Pamela",
    "Last Name": "Carlson"
  },
  {
    "First Name": "Ace",
    "Last Name": "Carlson"
  },
  {
    "First Name": "Mary",
    "Last Name": "Carpenter"
  },
  {
    "First Name": "Emma",
    "Last Name": "Carrell"
  },
  {
    "First Name": "Hayden",
    "Last Name": "Cason"
  },
  {
    "First Name": "Luis",
    "Last Name": "Castellanos"
  },
  {
    "First Name": "Dominic",
    "Last Name": "Cerullo"
  },
  {
    "First Name": "Emily",
    "Last Name": "Chan"
  },
  {
    "First Name": "Juliette",
    "Last Name": "Chan"
  },
  {
    "First Name": "Shepperd",
    "Last Name": "Chandler"
  },
  {
    "First Name": "Riley",
    "Last Name": "Chang"
  },
  {
    "First Name": "Marguerite",
    "Last Name": "Chavoya"
  },
  {
    "First Name": "Matthew",
    "Last Name": "Choi"
  },
  {
    "First Name": "Benjamin",
    "Last Name": "Christy"
  },
  {
    "First Name": "Renner",
    "Last Name": "Chu"
  },
  {
    "First Name": "Sophia",
    "Last Name": "Clark"
  },
  {
    "First Name": "Hiatt",
    "Last Name": "Clark"
  },
  {
    "First Name": "Cameron",
    "Last Name": "Clear"
  },
  {
    "First Name": "Henry",
    "Last Name": "Cohen"
  },
  {
    "First Name": "Kennedy",
    "Last Name": "Coleman"
  },
  {
    "First Name": "Sophia",
    "Last Name": "Colenso"
  },
  {
    "First Name": "Hayes",
    "Last Name": "Colter"
  },
  {
    "First Name": "Sara",
    "Last Name": "Colvin"
  },
  {
    "First Name": "Harrison",
    "Last Name": "Converse"
  },
  {
    "First Name": "John",
    "Last Name": "Cook"
  },
  {
    "First Name": "Jonas",
    "Last Name": "Corn"
  },
  {
    "First Name": "Maxwell",
    "Last Name": "Cracken"
  },
  {
    "First Name": "Abigail",
    "Last Name": "Crain"
  },
  {
    "First Name": "Emma",
    "Last Name": "Cruz Melo"
  },
  {
    "First Name": "Mateo",
    "Last Name": "Cura"
  },
  {
    "First Name": "Hazel",
    "Last Name": "Dallas-Hefflefinger"
  },
  {
    "First Name": "Ava",
    "Last Name": "Daniels"
  },
  {
    "First Name": "Graeson",
    "Last Name": "Davis"
  },
  {
    "First Name": "Sadie",
    "Last Name": "Davis"
  },
  {
    "First Name": "Grayson",
    "Last Name": "Davis"
  },
  {
    "First Name": "Sachin",
    "Last Name": "Dayalji"
  },
  {
    "First Name": "Juliet",
    "Last Name": "Deadman"
  },
  {
    "First Name": "Katherine",
    "Last Name": "Deeken"
  },
  {
    "First Name": "Mollie",
    "Last Name": "DeLay"
  },
  {
    "First Name": "Ean",
    "Last Name": "Dennis"
  },
  {
    "First Name": "Tate",
    "Last Name": "Deskin"
  },
  {
    "First Name": "Grace",
    "Last Name": "Dethlefsen"
  },
  {
    "First Name": "Maxime",
    "Last Name": "Diaz Mathe"
  },
  {
    "First Name": "Anna",
    "Last Name": "Doak"
  },
  {
    "First Name": "Perryman",
    "Last Name": "Doffermyre"
  },
  {
    "First Name": "Daisy",
    "Last Name": "Donaldson"
  },
  {
    "First Name": "Mattie",
    "Last Name": "Donnan"
  },
  {
    "First Name": "Desmond-John",
    "Last Name": "Donohoe-Hamill"
  },
  {
    "First Name": "John",
    "Last Name": "Drennan"
  },
  {
    "First Name": "Shenghe",
    "Last Name": "Du"
  },
  {
    "First Name": "Catherine",
    "Last Name": "Duhon"
  },
  {
    "First Name": "Thomas",
    "Last Name": "Dyer"
  },
  {
    "First Name": "Emily",
    "Last Name": "Egan"
  },
  {
    "First Name": "Marcum",
    "Last Name": "Enfield"
  },
  {
    "First Name": "Espen",
    "Last Name": "Enoksen"
  },
  {
    "First Name": "Holden",
    "Last Name": "Eppler"
  },
  {
    "First Name": "Andrew",
    "Last Name": "Erman"
  },
  {
    "First Name": "Colesen",
    "Last Name": "Evans"
  },
  {
    "First Name": "Cameron",
    "Last Name": "Evans"
  },
  {
    "First Name": "Olivia",
    "Last Name": "Evans"
  },
  {
    "First Name": "Ava",
    "Last Name": "Ewing"
  },
  {
    "First Name": "Lucas",
    "Last Name": "Fabris"
  },
  {
    "First Name": "Isabel",
    "Last Name": "Feigenbaum"
  },
  {
    "First Name": "Asher",
    "Last Name": "Ferdows"
  },
  {
    "First Name": "Hayes",
    "Last Name": "Fetter"
  },
  {
    "First Name": "Hadlie",
    "Last Name": "Fidler"
  },
  {
    "First Name": "Ellis",
    "Last Name": "Finney"
  },
  {
    "First Name": "Finnley",
    "Last Name": "Fisher"
  },
  {
    "First Name": "Eva",
    "Last Name": "Fishman"
  },
  {
    "First Name": "Blythe",
    "Last Name": "Fitzgerald"
  },
  {
    "First Name": "Thrit",
    "Last Name": "Fitzgerald"
  },
  {
    "First Name": "Liam",
    "Last Name": "Flanagan"
  },
  {
    "First Name": "Jax",
    "Last Name": "Florez"
  },
  {
    "First Name": "Nicholas",
    "Last Name": "Fontenot"
  },
  {
    "First Name": "Robert",
    "Last Name": "Forshee"
  },
  {
    "First Name": "William",
    "Last Name": "Foster"
  },
  {
    "First Name": "Alexandra",
    "Last Name": "Freeman"
  },
  {
    "First Name": "Michael",
    "Last Name": "Friedrich"
  },
  {
    "First Name": "Makynzie",
    "Last Name": "Fristoe"
  },
  {
    "First Name": "Benjamin",
    "Last Name": "Garancis"
  },
  {
    "First Name": "Sarah",
    "Last Name": "Gates"
  },
  {
    "First Name": "Benjamin",
    "Last Name": "Gates"
  },
  {
    "First Name": "Eleanor",
    "Last Name": "Gates"
  },
  {
    "First Name": "Austin",
    "Last Name": "Gawley"
  },
  {
    "First Name": "Joshua",
    "Last Name": "George"
  },
  {
    "First Name": "Sloane",
    "Last Name": "George"
  },
  {
    "First Name": "Thompson",
    "Last Name": "Gerard"
  },
  {
    "First Name": "Brooks",
    "Last Name": "Gerken"
  },
  {
    "First Name": "Molly",
    "Last Name": "Gerstenhaber"
  },
  {
    "First Name": "Carle-Joseph",
    "Last Name": "Giesen"
  },
  {
    "First Name": "Madeleine",
    "Last Name": "Gilbert"
  },
  {
    "First Name": "Bruno",
    "Last Name": "Gill"
  },
  {
    "First Name": "Chloe",
    "Last Name": "Gilmore"
  },
  {
    "First Name": "Emma",
    "Last Name": "Gilmore"
  },
  {
    "First Name": "Rosemary",
    "Last Name": "Gilmore"
  },
  {
    "First Name": "Daniel",
    "Last Name": "Gonzales"
  },
  {
    "First Name": "Grace",
    "Last Name": "Goodwin"
  },
  {
    "First Name": "John",
    "Last Name": "Greco"
  },
  {
    "First Name": "WILLIAM",
    "Last Name": "GRIFFIN"
  },
  {
    "First Name": "Evan",
    "Last Name": "Gross"
  },
  {
    "First Name": "Levi",
    "Last Name": "Gruber"
  },
  {
    "First Name": "William",
    "Last Name": "Gurganus"
  },
  {
    "First Name": "Coco",
    "Last Name": "Gutierrez"
  },
  {
    "First Name": "Marco",
    "Last Name": "Gutierrez"
  },
  {
    "First Name": "Kennedy",
    "Last Name": "Haefliger"
  },
  {
    "First Name": "Cody",
    "Last Name": "Hale"
  },
  {
    "First Name": "Whitney",
    "Last Name": "Hall"
  },
  {
    "First Name": "Avery",
    "Last Name": "Hamilton"
  },
  {
    "First Name": "Molly",
    "Last Name": "Hanna"
  },
  {
    "First Name": "Stephen",
    "Last Name": "Hanna"
  },
  {
    "First Name": "Lauren",
    "Last Name": "Harlow"
  },
  {
    "First Name": "Murdock",
    "Last Name": "Harman"
  },
  {
    "First Name": "Mary",
    "Last Name": "Harper"
  },
  {
    "First Name": "Gianella",
    "Last Name": "Hartman"
  },
  {
    "First Name": "Graham",
    "Last Name": "Hawkins"
  },
  {
    "First Name": "Dylan",
    "Last Name": "Hayes"
  },
  {
    "First Name": "Kinsey",
    "Last Name": "Hefton"
  },
  {
    "First Name": "Knox",
    "Last Name": "Heinlen"
  },
  {
    "First Name": "Everett",
    "Last Name": "Heis"
  },
  {
    "First Name": "Eli",
    "Last Name": "Helbing"
  },
  {
    "First Name": "Avery",
    "Last Name": "Hemphill"
  },
  {
    "First Name": "Sydney",
    "Last Name": "Herod"
  },
  {
    "First Name": "Hudson",
    "Last Name": "Herzog"
  },
  {
    "First Name": "John",
    "Last Name": "Hicks"
  },
  {
    "First Name": "Henry",
    "Last Name": "Hightower"
  },
  {
    "First Name": "Hazel",
    "Last Name": "Hinze"
  },
  {
    "First Name": "Elizabeth",
    "Last Name": "Ho"
  },
  {
    "First Name": "Conrad",
    "Last Name": "Hoaglund"
  },
  {
    "First Name": "Shaw",
    "Last Name": "Hoffmann"
  },
  {
    "First Name": "Audrey",
    "Last Name": "Hogue"
  },
  {
    "First Name": "Katelyn",
    "Last Name": "Hogue"
  },
  {
    "First Name": "Harrison",
    "Last Name": "Holland"
  },
  {
    "First Name": "Nova",
    "Last Name": "Holmstedt"
  },
  {
    "First Name": "Hadlin",
    "Last Name": "Honea"
  },
  {
    "First Name": "Orsella",
    "Last Name": "Hooks"
  },
  {
    "First Name": "Zoey",
    "Last Name": "Horne"
  },
  {
    "First Name": "Kinsley",
    "Last Name": "Horstman"
  },
  {
    "First Name": "Hayes",
    "Last Name": "Hortenstine"
  },
  {
    "First Name": "Blake",
    "Last Name": "Howard"
  },
  {
    "First Name": "Charles",
    "Last Name": "Howard"
  },
  {
    "First Name": "Carol",
    "Last Name": "Hrncir"
  },
  {
    "First Name": "Samuel",
    "Last Name": "Huff"
  },
  {
    "First Name": "Allie",
    "Last Name": "Iles"
  },
  {
    "First Name": "Blaire",
    "Last Name": "Inabnett"
  },
  {
    "First Name": "Charlie",
    "Last Name": "Isom"
  },
  {
    "First Name": "Emery",
    "Last Name": "Jeandron"
  },
  {
    "First Name": "Fulton",
    "Last Name": "Jefferies"
  },
  {
    "First Name": "Amelia",
    "Last Name": "Johnston"
  },
  {
    "First Name": "Gwennan",
    "Last Name": "Jones"
  },
  {
    "First Name": "Tianyi",
    "Last Name": "Kang"
  }
]
